Workbook
Name ACOInsight1: Inputs!$D$23:$D$24

Sheet Inputs
B1: Month Contract Starts | C1: 43647
B2: Contract Months | C2: 36
B3: Monthly or Quarterly? | C3: Quarterly
B4: Enable Old Pricing | C4: No
B5: Lead Office | C5: New York
D6: Population #1 | E6: Population #2 | F6: Population #3 | G6: Population #4 | H6: Population #5
B7: CCLF | D7: Y | L7: Y
B8: Collaborative Member Prior to 2017-07-01 | D8: N | L8: N
B9: Non-CMS Files | D9: N
B10: MARA Risk Score | D10: N
B11: Initial Estimated Lives | D11: 50000 | L11: Monthly
B12: Number of Datafeeds | D12: 1 | L12: Quarterly
B13: Datamart | D13: Y
B14: HCC Risk Scores | D14: N | L14: New York
B15: HCG Benchmarks | D15: N | L15: PRM
B16: PAC/Grouping/Benchmarks | D16: N
B17: Key Claims Metrics | D17: N | L17: Y
B18: Waste Calculator | D18: Y | L18: N
B19: Medical Conditions | D19: N | L19: Monthly
B20: PRM Oppourtunity Prospective Scores | D20: N
B21: PRM Conditions to Consider (Data Only - Dashboard Version) | D21: N | L21: Yes
B22: PRM Medicare ACO Analytics | D22: N | L22: No
B23: ACO Insight - Basic | D23: N
B24: ACO Insight - Enhanced | D24: Y
B25: PRM Care Coordinator Report | D25: N
B26: PRM Caregiver's Checklist | D26: N
B27: PRM Physician Risk and Credibility Adjusted Report | D27: N
B28: PRM PCP Dashboard | D28: N
B29: PRM Conditions to Consider Dashboards | D29: N
B30: Patient Flow | D30: N

Sheet Outputs_External
D2: Population #1 | E2: Population #2 | F2: Population #3 | G2: Population #4 | H2: Population #5
B3: One-Time Fees:
C4: Implementation | D4: =MAX(Calcs!D4, 0) -> 5000 | E4: =MAX(Calcs!E4, 0) -> 0 | F4: =MAX(Calcs!F4, 0) -> 0 | G4: =MAX(Calcs!G4, 0) -> 0 | H4: =MAX(Calcs!H4, 0) -> 0
B6: Annual Data Fees:
C7: Base Processing Fee | D7: =SUM(Calcs!D40, Calcs!D53) -> 15000 | E7: =SUM(Calcs!E40, Calcs!E53) -> 0 | F7: =SUM(Calcs!F40, Calcs!F53) -> 0 | G7: =SUM(Calcs!G40, Calcs!G53) -> 0 | H7: =SUM(Calcs!H40, Calcs!H53) -> 0
C8: HCC Risk Scores | D8: =SUM(Calcs!D41, Calcs!D54) -> 0 | E8: =SUM(Calcs!E41, Calcs!E54) -> 0 | F8: =SUM(Calcs!F41, Calcs!F54) -> 0 | G8: =SUM(Calcs!G41, Calcs!G54) -> 0 | H8: =SUM(Calcs!H41, Calcs!H54) -> 0
C9: HCG Benchmarks | D9: =SUM(Calcs!D42, Calcs!D55) -> 0 | E9: =SUM(Calcs!E42, Calcs!E55) -> 0 | F9: =SUM(Calcs!F42, Calcs!F55) -> 0 | G9: =SUM(Calcs!G42, Calcs!G55) -> 0 | H9: =SUM(Calcs!H42, Calcs!H55) -> 0
C10: PAC/Grouping/Benchmarks | D10: =SUM(Calcs!D43, Calcs!D56) -> 0 | E10: =SUM(Calcs!E43, Calcs!E56) -> 0 | F10: =SUM(Calcs!F43, Calcs!F56) -> 0 | G10: =SUM(Calcs!G43, Calcs!G56) -> 0 | H10: =SUM(Calcs!H43, Calcs!H56) -> 0
C11: Key Claims Metrics | D11: =SUM(Calcs!D44, Calcs!D57) -> 0 | E11: =SUM(Calcs!E44, Calcs!E57) -> 0 | F11: =SUM(Calcs!F44, Calcs!F57) -> 0 | G11: =SUM(Calcs!G44, Calcs!G57) -> 0 | H11: =SUM(Calcs!H44, Calcs!H57) -> 0
C12: Waste Calculator | D12: =SUM(Calcs!D45, Calcs!D58) -> 0 | E12: =SUM(Calcs!E45, Calcs!E58) -> 0 | F12: =SUM(Calcs!F45, Calcs!F58) -> 0 | G12: =SUM(Calcs!G45, Calcs!G58) -> 0 | H12: =SUM(Calcs!H45, Calcs!H58) -> 0
C13: Medical Conditions | D13: =SUM(Calcs!D46, Calcs!D59) -> 0 | E13: =SUM(Calcs!E46, Calcs!E59) -> 0 | F13: =SUM(Calcs!F46, Calcs!F59) -> 0 | G13: =SUM(Calcs!G46, Calcs!G59) -> 0 | H13: =SUM(Calcs!H46, Calcs!H59) -> 0
C14: PRM Oppourtunity Prospective Scores | D14: =SUM(Calcs!D48, Calcs!D61) -> 0 | E14: =SUM(Calcs!E48, Calcs!E61) -> 0 | F14: =SUM(Calcs!F48, Calcs!F61) -> 0 | G14: =SUM(Calcs!G48, Calcs!G61) -> 0 | H14: =SUM(Calcs!H48, Calcs!H61) -> 0
C15: PRM Conditions to Consider (Data Only) | D15: =SUM(Calcs!D49, Calcs!D62) -> 0 | E15: =SUM(Calcs!E49, Calcs!E62) -> 0 | F15: =SUM(Calcs!F49, Calcs!F62) -> 0 | G15: =SUM(Calcs!G49, Calcs!G62) -> 0 | H15: =SUM(Calcs!H49, Calcs!H62) -> 0
C16: PRM Medicare ACO Analytics (CCLF Only) | D16: =SUM(Calcs!D50, Calcs!D63, Calcs!D47, Calcs!D60) -> 0 | E16: =SUM(Calcs!E50, Calcs!E63, Calcs!E47, Calcs!E60) -> 0 | F16: =SUM(Calcs!F50, Calcs!F63, Calcs!F47, Calcs!F60) -> 0 | G16: =SUM(Calcs!G50, Calcs!G63, Calcs!G47, Calcs!G60) -> 0 | H16: =SUM(Calcs!H50, Calcs!H63, Calcs!H47, Calcs!H60) -> 0
B18: Annual Product Fees
C19: ACO Insight - Basic | D19: =SUM(Calcs!D66, Calcs!D77) -> 0 | E19: =SUM(Calcs!E66, Calcs!E77) -> 0 | F19: =SUM(Calcs!F66, Calcs!F77) -> 0 | G19: =SUM(Calcs!G66, Calcs!G77) -> 0 | H19: =SUM(Calcs!H66, Calcs!H77) -> 0
C20: ACO Insight - Enhanced | D20: =SUM(Calcs!D67, Calcs!D78) -> 33000 | E20: =SUM(Calcs!E67, Calcs!E78) -> 0 | F20: =SUM(Calcs!F67, Calcs!F78) -> 0 | G20: =SUM(Calcs!G67, Calcs!G78) -> 0 | H20: =SUM(Calcs!H67, Calcs!H78) -> 0
C21: PRM Care Coordinator Report | D21: =SUM(Calcs!D68, Calcs!D79) -> 0 | E21: =SUM(Calcs!E68, Calcs!E79) -> 0 | F21: =SUM(Calcs!F68, Calcs!F79) -> 0 | G21: =SUM(Calcs!G68, Calcs!G79) -> 0 | H21: =SUM(Calcs!H68, Calcs!H79) -> 0
C22: PRM Caregiver's Checklist | D22: =SUM(Calcs!D69, Calcs!D80) -> 0 | E22: =SUM(Calcs!E69, Calcs!E80) -> 0 | F22: =SUM(Calcs!F69, Calcs!F80) -> 0 | G22: =SUM(Calcs!G69, Calcs!G80) -> 0 | H22: =SUM(Calcs!H69, Calcs!H80) -> 0
C23: PRM Physician Risk and Credibility Adjusted Report | D23: =SUM(Calcs!D70, Calcs!D81) -> 0 | E23: =SUM(Calcs!E70, Calcs!E81) -> 0 | F23: =SUM(Calcs!F70, Calcs!F81) -> 0 | G23: =SUM(Calcs!G70, Calcs!G81) -> 0 | H23: =SUM(Calcs!H70, Calcs!H81) -> 0
C24: PRM PCP Dashboard | D24: =SUM(Calcs!D71, Calcs!D82) -> 0 | E24: =SUM(Calcs!E71, Calcs!E82) -> 0 | F24: =SUM(Calcs!F71, Calcs!F82) -> 0 | G24: =SUM(Calcs!G71, Calcs!G82) -> 0 | H24: =SUM(Calcs!H71, Calcs!H82) -> 0
C25: PRM Conditions to Consider Dashboards | D25: =SUM(Calcs!D72, Calcs!D83) -> 0 | E25: =SUM(Calcs!E72, Calcs!E83) -> 0 | F25: =SUM(Calcs!F72, Calcs!F83) -> 0 | G25: =SUM(Calcs!G72, Calcs!G83) -> 0 | H25: =SUM(Calcs!H72, Calcs!H83) -> 0
C26: Patient Flow | D26: =SUM(Calcs!D73, Calcs!D84) -> 0 | E26: =SUM(Calcs!E73, Calcs!E84) -> 0 | F26: =SUM(Calcs!F73, Calcs!F84) -> 0 | G26: =SUM(Calcs!G73, Calcs!G84) -> 0 | H26: =SUM(Calcs!H73, Calcs!H84) -> 0
C27: Datamart | D27: =SUM(Calcs!D74, Calcs!D85) -> 9600 | E27: =SUM(Calcs!E74, Calcs!E85) -> 0 | F27: =SUM(Calcs!F74, Calcs!F85) -> 0 | G27: =SUM(Calcs!G74, Calcs!G85) -> 0 | H27: =SUM(Calcs!H74, Calcs!H85) -> 0
B29: Discounts
C30: Product Discounts | D30: =SUM(Calcs!D110:D114) -> -2880 | E30: =SUM(Calcs!E110:E114) -> 0 | F30: =SUM(Calcs!F110:F114) -> 0 | G30: =SUM(Calcs!G110:G114) -> 0 | H30: =SUM(Calcs!H110:H114) -> 0
C31: Population Discounts | D31: =Calcs!D120 -> 0 | E31: =Calcs!E120 -> 0 | F31: =Calcs!F120 -> 0 | G31: =Calcs!G120 -> 0 | H31: =Calcs!H120 -> 0
C32: Existing Collaborative Discount | D32: =Calcs!D122 -> 0 | E32: 0 | F32: 0 | G32: 0 | H32: 0
B34: Annual Total | D34: =SUM(D7:D16, D19:D27, D30:D32) -> 54720 | E34: =SUM(E7:E16, E19:E27, E30:E31) -> 0 | F34: =SUM(F7:F16, F19:F27, F30:F31) -> 0 | G34: =SUM(G7:G16, G19:G27, G30:G31) -> 0 | H34: =SUM(H7:H16, H19:H27, H30:H31) -> 0
D35: =D34/4 -> 13680
B36: Price inflation multiplier
C37: =INDEX(Outputs_Timeline!$D$3:$D$94,MATCH(Inputs!$C$1,Outputs_Timeline!$B$3:$B$94,0),1) -> 1.0125
B39: MARA Contract Total
C40: Year One | D40: =IF(Inputs!D$10 = "Y", SUMIF(Outputs_Timeline!$B$3:$B$204,"<" & EDATE(Inputs!$C$1,12), Outputs_Timeline!AD$3:AD$204), 0) -> 0 | E40: =IF(Inputs!E$10 = "Y", SUMIF(Outputs_Timeline!$B$3:$B$204,"<" & EDATE(Inputs!$C$1,12), Outputs_Timeline!AE$3:AE$204), 0) -> 0 | F40: =IF(Inputs!F$10 = "Y", SUMIF(Outputs_Timeline!$B$3:$B$204,"<" & EDATE(Inputs!$C$1,12), Outputs_Timeline!AF$3:AF$204), 0) -> 0 | G40: =IF(Inputs!G$10 = "Y", SUMIF(Outputs_Timeline!$B$3:$B$204,"<" & EDATE(Inputs!$C$1,12), Outputs_Timeline!AG$3:AG$204), 0) -> 0 | H40: =IF(Inputs!H$10 = "Y", SUMIF(Outputs_Timeline!$B$3:$B$204,"<" & EDATE(Inputs!$C$1,12), Outputs_Timeline!AH$3:AH$204), 0) -> 0
C41: Contract Total | D41: =IF(Inputs!D$10 = "Y", SUM(Outputs_Timeline!AD$3:AD$204), 0) -> 0 | E41: =IF(Inputs!E$10 = "Y", SUM(Outputs_Timeline!AE$3:AE$204), 0) -> 0 | F41: =IF(Inputs!F$10 = "Y", SUM(Outputs_Timeline!AF$3:AF$204), 0) -> 0 | G41: =IF(Inputs!G$10 = "Y", SUM(Outputs_Timeline!AG$3:AG$204), 0) -> 0 | H41: =IF(Inputs!H$10 = "Y", SUM(Outputs_Timeline!AH$3:AH$204), 0) -> 0
B43: Prorated Total with Implementation | D43: =(D34/12*Inputs!$C$2+D4)*$C$37+D41 -> 171274.5 | E43: =(E34/12*Inputs!$C$2+E4)*$C$37+E41 -> 0 | F43: =(F34/12*Inputs!$C$2+F4)*$C$37+F41 -> 0 | G43: =(G34/12*Inputs!$C$2+G4)*$C$37+G41 -> 0 | H43: =(H34/12*Inputs!$C$2+H4)*$C$37+H41 -> 0
B46: Total across entire contract duration
C47: =SUM(Outputs_Timeline!W:W) -> 171274.5
C48: =SUM(D43:H43) -> 171274.5

Sheet Outputs_Internal
F1: Revenue Split Percentages
D2: Totals | F2: New York | G2: PRM | H2: MI Royalties | I2: Other Royalties | K2: New York | L2: PRM | M2: MI Royalties | N2: Other Royalties
B3: One-Time Fees:
C4: Implementation (CCLF) | D4: =SUMIF(Inputs!$D$7:$H$7, "Y", Outputs_External!D4:'Outputs_External'!H4) -> 5000 | F4: 0.5 | G4: 0.5 | H4: =1-SUM(F4:G4) -> 0 | I4: 0 | K4: =F4*$D4 -> 2500 | L4: =G4*$D4 -> 2500 | M4: =H4*$D4 -> 0 | N4: =I4*$D4 -> 0
C5: Implementation (non-CCLF) | D5: =SUMIF(Inputs!$D$7:$H$7, "N", Outputs_External!D4:'Outputs_External'!H4) -> 0 | F5: 0.1 | G5: 0.9 | H5: =1-SUM(F5:G5) -> 0 | I5: 0 | K5: =F5*$D5 -> 0 | L5: =G5*$D5 -> 0 | M5: =H5*$D5 -> 0 | N5: =I5*$D5 -> 0
D7: Base processing fee shift: | H7: 0.075
B9: Annual Base Data Fees (with implicit forces):
C10: Base Processing Fee | D10: =SUM(Calcs!D14:H14) -> 15000 | F10: 0.4 | G10: 0.6 | H10: =1-SUM(F10:G10) -> 0 | I10: 0 | K10: =(IF(Inputs!C5="New York",$H$7,-$H$7)+F10)*$D10 -> 7125 | L10: =(IF(Inputs!C5="New York",-$H$7,$H$7)+G10)*D10 -> 7875 | M10: =H10*$D10 -> 0 | N10: =I10*$D10 -> 0
C11: HCC Risk Scores | D11: =SUM(Calcs!D15:H15) -> 1000 | F11: 0.1 | G11: 0.9 | H11: =1-SUM(F11:G11) -> 0 | I11: 0 | K11: =F11*$D11 -> 100 | L11: =G11*$D11 -> 900 | M11: =H11*$D11 -> 0 | N11: =I11*$D11 -> 0
C12: HCG Benchmarks | D12: =SUM(Calcs!D16:H16) -> 4000 | F12: 0.45 | G12: 0.45 | H12: 0 | I12: 0.1 | K12: =F12*$D12 -> 1800 | L12: =G12*$D12 -> 1800 | M12: =H12*$D12 -> 0 | N12: =I12*$D12 -> 400
C13: PAC/Grouping/Benchmarks | D13: =SUM(Calcs!D17:H17) -> 2000 | F13: 0.9 | G13: 0.1 | H13: =1-SUM(F13:G13) -> 0 | I13: 0 | K13: =F13*$D13 -> 1800 | L13: =G13*$D13 -> 200 | M13: =H13*$D13 -> 0 | N13: =I13*$D13 -> 0
C14: Key Claims Metrics | D14: =SUM(Calcs!D18:H18) -> 2000 | F14: 0.65 | G14: 0.35 | H14: =1-SUM(F14:G14) -> 0 | I14: 0 | K14: =F14*$D14 -> 1300 | L14: =G14*$D14 -> 700 | M14: =H14*$D14 -> 0 | N14: =I14*$D14 -> 0
C15: Waste Calculator | D15: =SUM(Calcs!D19:H19) -> 6000 | F15: 0.5 | G15: 0.5 | H15: 0 | I15: 0 | K15: =F15*$D15 -> 3000 | L15: =G15*$D15 -> 3000 | M15: =H15*$D15 -> 0 | N15: =I15*$D15 -> 0
C16: Medical Conditions | D16: =SUM(Calcs!D20:H20) -> 4000 | F16: 0.9 | G16: 0.1 | H16: =1-SUM(F16:G16) -> 0 | I16: 0 | K16: =F16*$D16 -> 3600 | L16: =G16*$D16 -> 400 | M16: =H16*$D16 -> 0 | N16: =I16*$D16 -> 0
C17: Quality Measures | D17: =SUM(Calcs!D21:H21) -> 0 | F17: 0.1 | G17: 0.9 | H17: 0 | I17: 0 | K17: =F17*$D17 -> 0 | L17: =G17*$D17 -> 0 | M17: =H17*$D17 -> 0 | N17: =I17*$D17 -> 0
C18: PRM Oppourtunity Prospective Scores | D18: =SUM(Calcs!D22:H22) -> 0 | F18: 0.1 | G18: 0.9 | H18: =1-SUM(F18:G18) -> 0 | I18: 0 | K18: =F18*$D18 -> 0 | L18: =G18*$D18 -> 0 | M18: =H18*$D18 -> 0 | N18: =I18*$D18 -> 0
C19: PRM Conditions to Consider (Data Only) | D19: =SUM(Calcs!D23:H23) -> 0 | F19: 0.1 | G19: 0.9 | H19: =1-SUM(F19:G19) -> 0 | I19: 0 | K19: =F19*$D19 -> 0 | L19: =G19*$D19 -> 0 | M19: =H19*$D19 -> 0 | N19: =I19*$D19 -> 0
C20: PRM Medicare ACO Analytics (CCLF Only) | D20: =SUM(Calcs!D24:H24) -> 0 | F20: 0.1 | G20: 0.9 | H20: =1-SUM(F20:G20) -> 0 | I20: 0 | K20: =F20*$D20 -> 0 | L20: =G20*$D20 -> 0 | M20: =H20*$D20 -> 0 | N20: =I20*$D20 -> 0
G22: PRM Increase on PMPY Add-on fees: | H22: 0.075
B24: Annual PMPM Add-on Data Fees (with implicit forces):
C25: Base Processing Fee | D25: =SUM(Calcs!D27:H27) -> 0 | F25: =(1-G25)*F10/SUM(F10,H10) -> 0.325 | G25: =MIN(1,G10+$H$22) -> 0.675 | H25: =IF(H10=0, 0,(1-G25)*H10/SUM(F10,H10)) -> 0 | I25: =IF(I10=0, 0,(1-G25)*I10/SUM(F10,I10)) -> 0 | K25: =(IF(Inputs!C5="New York",$H$7,-$H$7)+F25)*$D25 -> 0 | L25: =(IF(Inputs!C5="New York",-$H$7,$H$7)+G25)*$D25 -> 0 | M25: =H25*$D25 -> 0 | N25: =I25*$D25 -> 0
C26: HCC Risk Scores | D26: =SUM(Calcs!D28:H28) -> 0 | F26: =(1-G26)*F11/SUM(F11,H11) -> 0.025 | G26: =MIN(1,G11+$H$22) -> 0.975 | H26: =IF(H11=0, 0,(1-G26)*H11/SUM(F11,H11)) -> 0 | I26: =IF(I11=0, 0,(1-G26)*I11/SUM(F11,I11)) -> 0 | K26: =F26*$D26 -> 0 | L26: =G26*$D26 -> 0 | M26: =H26*$D26 -> 0 | N26: =I26*$D26 -> 0
C27: HCG Benchmarks | D27: =SUM(Calcs!D29:H29) -> 0 | F27: =(1-G27)*F12/SUM(F12,H12, I12) -> 0.38863636 | G27: =MIN(1,G12+$H$22) -> 0.525 | H27: =IF(H12=0, 0,(1-G27)*H12/SUM(F12,H12)) -> 0 | I27: =IF(I12=0, 0,(1-G27)*I12/SUM(F12,I12)) -> 0.086363636 | K27: =F27*$D27 -> 0 | L27: =G27*$D27 -> 0 | M27: =H27*$D27 -> 0 | N27: =I27*$D27 -> 0
C28: PAC/Grouping/Benchmarks | D28: =SUM(Calcs!D30:H30) -> 0 | F28: =(1-G28)*F13/SUM(F13,H13) -> 0.825 | G28: =MIN(1,G13+$H$22) -> 0.175 | H28: =IF(H13=0, 0,(1-G28)*H13/SUM(F13,H13)) -> 0 | I28: =IF(I13=0, 0,(1-G28)*I13/SUM(F13,I13)) -> 0 | K28: =F28*$D28 -> 0 | L28: =G28*$D28 -> 0 | M28: =H28*$D28 -> 0 | N28: =I28*$D28 -> 0
C29: Key Claims Metrics | D29: =SUM(Calcs!D31:H31) -> 0 | F29: =(1-G29)*F14/SUM(F14,H14) -> 0.575 | G29: =MIN(1,G14+$H$22) -> 0.425 | H29: =IF(H14=0, 0,(1-G29)*H14/SUM(F14,H14)) -> 0 | I29: =IF(I14=0, 0,(1-G29)*I14/SUM(F14,I14)) -> 0 | K29: =F29*$D29 -> 0 | L29: =G29*$D29 -> 0 | M29: =H29*$D29 -> 0 | N29: =I29*$D29 -> 0
C30: Waste Calculator | D30: =SUM(Calcs!D32:H32) -> 0 | F30: =(1-G30)*F15/SUM(F15,H15) -> 0.425 | G30: =MIN(1,G15+$H$22) -> 0.575 | H30: =IF(H15=0, 0,(1-G30)*H15/SUM(F15,H15)) -> 0 | I30: =IF(I15=0, 0,(1-G30)*I15/SUM(F15,I15)) -> 0 | K30: =F30*$D30 -> 0 | L30: =G30*$D30 -> 0 | M30: =H30*$D30 -> 0 | N30: =I30*$D30 -> 0
C31: Medical Conditions | D31: =SUM(Calcs!D33:H33) -> 0 | F31: =(1-G31)*F16/SUM(F16,H16) -> 0.825 | G31: =MIN(1,G16+$H$22) -> 0.175 | H31: =IF(H16=0, 0,(1-G31)*H16/SUM(F16,H16)) -> 0 | I31: =IF(I16=0, 0,(1-G31)*I16/SUM(F16,I16)) -> 0 | K31: =F31*$D31 -> 0 | L31: =G31*$D31 -> 0 | M31: =H31*$D31 -> 0 | N31: =I31*$D31 -> 0
C32: Quality Measures | D32: =SUM(Calcs!D34:H34) -> 0 | F32: =(1-G32)*F17/SUM(F17,H17) -> 0.025 | G32: =MIN(1,G17+$H$22) -> 0.975 | H32: =IF(H17=0, 0,(1-G32)*H17/SUM(F17,H17)) -> 0 | I32: =IF(I17=0, 0,(1-G32)*I17/SUM(F17,I17)) -> 0 | K32: =F32*$D32 -> 0 | L32: =G32*$D32 -> 0 | M32: =H32*$D32 -> 0 | N32: =I32*$D32 -> 0
C33: PRM Oppourtunity Prospective Scores | D33: =SUM(Calcs!D35:H35) -> 0 | F33: =(1-G33)*F18/SUM(F18,H18) -> 0.025 | G33: =MIN(1,G18+$H$22) -> 0.975 | H33: =IF(H18=0, 0,(1-G33)*H18/SUM(F18,H18)) -> 0 | I33: =IF(I18=0, 0,(1-G33)*I18/SUM(F18,I18)) -> 0 | K33: =F33*$D33 -> 0 | L33: =G33*$D33 -> 0 | M33: =H33*$D33 -> 0 | N33: =I33*$D33 -> 0
C34: PRM Conditions to Consider (Data Only) | D34: =SUM(Calcs!D36:H36) -> 0 | F34: =(1-G34)*F19/SUM(F19,H19) -> 0.025 | G34: =MIN(1,G19+$H$22) -> 0.975 | H34: =IF(H19=0, 0,(1-G34)*H19/SUM(F19,H19)) -> 0 | I34: =IF(I19=0, 0,(1-G34)*I19/SUM(F19,I19)) -> 0 | K34: =F34*$D34 -> 0 | L34: =G34*$D34 -> 0 | M34: =H34*$D34 -> 0 | N34: =I34*$D34 -> 0
C35: PRM Medicare ACO Analytics (CCLF Only) | D35: =SUM(Calcs!D37:H37) -> 0 | F35: =(1-G35)*F20/SUM(F20,H20) -> 0.025 | G35: =MIN(1,G20+$H$22) -> 0.975 | H35: =IF(H20=0, 0,(1-G35)*H20/SUM(F20,H20)) -> 0 | I35: =IF(I20=0, 0,(1-G35)*I20/SUM(F20,I20)) -> 0 | K35: =F35*$D35 -> 0 | L35: =G35*$D35 -> 0 | M35: =H35*$D35 -> 0 | N35: =I35*$D35 -> 0
B37: Annual Base Product Fees (Marginal over data fees)
C38: ACO Insight - Basic | D38: =SUM(Calcs!D88:H88) -> 0 | F38: 0.9 | G38: 0.1 | H38: =1-SUM(F38:G38) -> 0 | I38: 0 | K38: =F38*$D38 -> 0 | L38: =G38*$D38 -> 0 | M38: =H38*$D38 -> 0 | N38: =I38*$D38 -> 0
C39: ACO Insight - Enhanced | D39: =SUM(Calcs!D89:H89) -> 14000 | F39: 0.9 | G39: 0.1 | H39: =1-SUM(F39:G39) -> 0 | I39: 0 | K39: =F39*$D39 -> 12600 | L39: =G39*$D39 -> 1400 | M39: =H39*$D39 -> 0 | N39: =I39*$D39 -> 0
C40: PRM Care Coordinator Report | D40: =SUM(Calcs!D90:H90) -> 0 | F40: 0.1 | G40: 0.9 | H40: =1-SUM(F40:G40) -> 0 | I40: 0 | K40: =F40*$D40 -> 0 | L40: =G40*$D40 -> 0 | M40: =H40*$D40 -> 0 | N40: =I40*$D40 -> 0
C41: PRM Caregiver's Checklist | D41: =SUM(Calcs!D91:H91) -> 0 | F41: 0.1 | G41: 0.9 | H41: 0 | I41: 0 | K41: =F41*$D41 -> 0 | L41: =G41*$D41 -> 0 | M41: =H41*$D41 -> 0 | N41: =I41*$D41 -> 0
C42: PRM Physician Risk and Credibility Adjusted Report | D42: =SUM(Calcs!D92:H92) -> 0 | F42: 0.1 | G42: 0.9 | H42: =1-SUM(F42:G42) -> 0 | I42: 0 | K42: =F42*$D42 -> 0 | L42: =G42*$D42 -> 0 | M42: =H42*$D42 -> 0 | N42: =I42*$D42 -> 0
C43: PRM PCP Dashboard | D43: =SUM(Calcs!D93:H93) -> 0 | F43: 0.1 | G43: 0.9 | H43: =1-SUM(F43:G43) -> 0 | I43: 0 | K43: =F43*$D43 -> 0 | L43: =G43*$D43 -> 0 | M43: =H43*$D43 -> 0 | N43: =I43*$D43 -> 0
C44: PRM Conditions to Consider Dashboards | D44: =SUM(Calcs!D94:H94) -> 0 | F44: 0.1 | G44: 0.9 | H44: =1-SUM(F44:G44) -> 0 | I44: 0 | K44: =F44*$D44 -> 0 | L44: =G44*$D44 -> 0 | M44: =H44*$D44 -> 0 | N44: =I44*$D44 -> 0
C45: Patient Flow | D45: =SUM(Calcs!D95:H95) -> 0 | F45: 0.1 | G45: 0.9 | H45: =1-SUM(F45:G45) -> 0 | I45: 0 | K45: =F45*$D45 -> 0 | L45: =G45*$D45 -> 0 | M45: =H45*$D45 -> 0 | N45: =I45*$D45 -> 0
C46: Datamart | D46: =SUM(Calcs!D96:H96) -> 9600 | F46: 0.1 | G46: 0.9 | H46: =1-SUM(F46:G46) -> 0 | I46: 0 | K46: =F46*$D46 -> 960 | L46: =G46*$D46 -> 8640 | M46: =H46*$D46 -> 0 | N46: =I46*$D46 -> 0
B48: Annual PMPM Add-on Product Fees (Marginal over data fees)
C49: ACO Insight - Basic | D49: =SUM(Calcs!D99:H99) -> 0 | F49: =IFERROR((1-G49)*F38/SUM(F38,H38),0) -> 0.825 | G49: =MIN(1,G38+$H$22) -> 0.175 | H49: =IFERROR((1-G49)*H38/SUM(F38,H38),0) -> 0 | I49: 0 | K49: =F49*$D49 -> 0 | L49: =G49*$D49 -> 0 | M49: =H49*$D49 -> 0 | N49: =I49*$D49 -> 0
C50: ACO Insight - Enhanced | D50: =SUM(Calcs!D100:H100) -> 0 | F50: =IFERROR((1-G50)*F39/SUM(F39,H39),0) -> 0.825 | G50: =MIN(1,G39+$H$22) -> 0.175 | H50: =IFERROR((1-G50)*H39/SUM(F39,H39),0) -> 0 | I50: 0 | K50: =F50*$D50 -> 0 | L50: =G50*$D50 -> 0 | M50: =H50*$D50 -> 0 | N50: =I50*$D50 -> 0
C51: PRM Care Coordinator Report | D51: =SUM(Calcs!D101:H101) -> 0 | F51: =IFERROR((1-G51)*F40/SUM(F40,H40),0) -> 0.025 | G51: =MIN(1,G40+$H$22) -> 0.975 | H51: =IFERROR((1-G51)*H40/SUM(F40,H40),0) -> 0 | I51: 0 | K51: =F51*$D51 -> 0 | L51: =G51*$D51 -> 0 | M51: =H51*$D51 -> 0 | N51: =I51*$D51 -> 0
C52: PRM Caregiver's Checklist | D52: =SUM(Calcs!D102:H102) -> 0 | F52: =IFERROR((1-G52)*F41/SUM(F41,H41),0) -> 0.025 | G52: =MIN(1,G41+$H$22) -> 0.975 | H52: =IFERROR((1-G52)*H41/SUM(F41,H41),0) -> 0 | I52: 0 | K52: =F52*$D52 -> 0 | L52: =G52*$D52 -> 0 | M52: =H52*$D52 -> 0 | N52: =I52*$D52 -> 0
C53: PRM Physician Risk and Credibility Adjusted Report | D53: =SUM(Calcs!D103:H103) -> 0 | F53: =IFERROR((1-G53)*F42/SUM(F42,H42),0) -> 0.025 | G53: =MIN(1,G42+$H$22) -> 0.975 | H53: =IFERROR((1-G53)*H42/SUM(F42,H42),0) -> 0 | I53: 0 | K53: =F53*$D53 -> 0 | L53: =G53*$D53 -> 0 | M53: =H53*$D53 -> 0 | N53: =I53*$D53 -> 0
C54: PRM PCP Dashboard | D54: =SUM(Calcs!D104:H104) -> 0 | F54: =IFERROR((1-G54)*F43/SUM(F43,H43),0) -> 0.025 | G54: =MIN(1,G43+$H$22) -> 0.975 | H54: =IFERROR((1-G54)*H43/SUM(F43,H43),0) -> 0 | I54: 0 | K54: =F54*$D54 -> 0 | L54: =G54*$D54 -> 0 | M54: =H54*$D54 -> 0 | N54: =I54*$D54 -> 0
C55: PRM Conditions to Consider Dashboards | D55: =SUM(Calcs!D105:H105) -> 0 | F55: =IFERROR((1-G55)*F44/SUM(F44,H44),0) -> 0.025 | G55: =MIN(1,G44+$H$22) -> 0.975 | H55: =IFERROR((1-G55)*H44/SUM(F44,H44),0) -> 0 | I55: 0 | K55: =F55*$D55 -> 0 | L55: =G55*$D55 -> 0 | M55: =H55*$D55 -> 0 | N55: =I55*$D55 -> 0
C56: Patient Flow | D56: =SUM(Calcs!D106:H106) -> 0 | F56: =IFERROR((1-G56)*F45/SUM(F45,H45),0) -> 0.025 | G56: =MIN(1,G45+$H$22) -> 0.975 | H56: =IFERROR((1-G56)*H45/SUM(F45,H45),0) -> 0 | I56: 0 | K56: =F56*$D56 -> 0 | L56: =G56*$D56 -> 0 | M56: =H56*$D56 -> 0 | N56: =I56*$D56 -> 0
C57: Datamart | D57: =SUM(Calcs!D107:H107) -> 0 | F57: =IFERROR((1-G57)*F46/SUM(F46,H46),0) -> 0.025 | G57: =MIN(1,G46+$H$22) -> 0.975 | H57: =IFERROR((1-G57)*H46/SUM(F46,H46),0) -> 0 | I57: 0 | K57: =F57*$D57 -> 0 | L57: =G57*$D57 -> 0 | M57: =H57*$D57 -> 0 | N57: =I57*$D57 -> 0
B59: Discounts
C60: Product Discounts | D60: =SUM(Outputs_External!D30:'Outputs_External'!H30) -> -2880 | F60: =IFERROR(SUM(K74:K82)/SUM($K$74:$N$82), 0) -> 0.59061033 | G60: =IFERROR(SUM(L74:L82)/SUM($K$74:$N$82), 0) -> 0.4 | H60: =IFERROR(SUM(M74:M82)/SUM($K$74:$N$82), 0) -> 0 | I60: =IFERROR(SUM(N74:N82)/SUM($K$74:$N$82), 0) -> 0.0093896714 | K60: =F60*$D$60 -> -1700.9577 | L60: =G60*$D$60 -> -1152 | M60: =H60*$D$60 -> 0 | N60: =I60*$D$60 -> -27.042254
C61: Population Discounts | D61: =SUM(Outputs_External!D31:'Outputs_External'!H31) -> 0 | F61: =IFERROR(SUM(K10:K60)/SUM($K10:$N60), 0) -> 0.5589189 | G61: =IFERROR(SUM(L10:L60)/SUM($K10:$N60), 0) -> 0.43426535 | H61: =IFERROR(SUM(M10:M60)/SUM($K10:$N60), 0) -> 0 | I61: =1-F61-G61-H61 -> 0.0068157483 | K61: =F61*$D$61 -> 0 | L61: =G61*$D$61 -> 0 | M61: =H61*$D$61 -> 0 | N61: =I61*$D$61 -> 0
C62: Existing Collaborative Discount | D62: =Outputs_External!D32 -> 0 | F62: 0.63 | G62: 0.37 | H62: 0 | I62: 0 | K62: =$D$62*F62 -> 0 | L62: =$D$62*G62 -> 0 | M62: =$D$62*H62 -> 0 | N62: =$D$62*I62 -> 0
B64: Annual Total | D64: =SUM(Outputs_External!D34:'Outputs_External'!H34) -> 54720 | K64: =SUM(K60:K62, K38:K46, K10:K20,K25:K35,K49:K57) -> 30584.042 | L64: =SUM(L60:L62, L38:L46, L10:L20,L25:L35,L49:L57) -> 23763 | M64: =SUM(M60:M62, M38:M46, M10:M20,M25:M35,M49:M57) -> 0 | N64: =SUM(N60:N62, N38:N46, N10:N20,N25:N35,N49:N57) -> 372.95775
C65: Reconcile | D65: =SUM(K64:N64) -> 54720
B67: MARA (Contract Total) | D67: =SUM(Outputs_Timeline!N:N) -> 0 | F67: ='MARA Prices'!$F$5 -> 0.1 | G67: ='MARA Prices'!$F$6 -> 0.1 | H67: 0 | I67: ='MARA Prices'!$F$4 -> 0.8 | K67: =$D$67*F67 -> 0 | L67: =$D$67*G67 -> 0 | M67: =$D$67*H67 -> 0 | N67: =$D$67*I67 -> 0
B69: Total across entire contract duration | D69: =SUM(Outputs_Timeline!W:W) -> 171274.5 | K69: =SUM(Outputs_Timeline!X:X) -> 95430.278 | L69: =SUM(Outputs_Timeline!Y:Y) -> 74711.363 | M69: =SUM(Outputs_Timeline!Z:Z) -> 0 | N69: =SUM(Outputs_Timeline!AA:AA) -> 1132.8592
K70: =IFERROR(K69/$D$69, 0) -> 0.55717739 | L70: =IFERROR(L69/$D$69, 0) -> 0.43620832 | M70: =IFERROR(M69/$D$69, 0) -> 0 | N70: =IFERROR(N69/$D$69, 0) -> 0.0066142897
B73: Annual Product Fees (Full fees)
C74: ACO Insight - Basic | D74: =SUM(Calcs!D66:H66)+SUM(Calcs!D77:H77) -> 0 | F74: =F38 -> 0.9 | G74: =G38 -> 0.1 | H74: =H38 -> 0 | I74: =I38 -> 0 | K74: =F74*$D74 -> 0 | L74: =G74*$D74 -> 0 | M74: =H74*$D74 -> 0 | N74: =I74*$D74 -> 0
C75: ACO Insight - Enhanced | D75: =SUM(Calcs!D67:H67)+SUM(Calcs!D78:H78) -> 33000 | F75: =IFERROR(SUM(K$39,K$11:K$16,K$50,K$26:K$31)/SUM($K$39:$N$39,$K$11:$N$16,$K$50:$N$50,$K$26:$N$31),0) -> 0.73333333 | G75: =IFERROR(SUM(L$39,L$11:L$16,L$50,L$26:L$31)/SUM($K$39:$N$39,$K$11:$N$16,$K$50:$N$50,$K$26:$N$31),0) -> 0.25454545 | H75: =IFERROR(SUM(M$39,M$11:M$16,M$50,M$26:M$31)/SUM($K$39:$N$39,$K$11:$N$16,$K$50:$N$50,$K$26:$N$31),0) -> 0 | I75: =IFERROR(SUM(N$39,N$11:N$16,N$50,N$26:N$31)/SUM($K$39:$N$39,$K$11:$N$16,$K$50:$N$50,$K$26:$N$31),0) -> 0.012121212 | K75: =F75*$D75 -> 24200 | L75: =G75*$D75 -> 8400 | M75: =H75*$D75 -> 0 | N75: =I75*$D75 -> 400
C76: PRM Care Coordinator Report | D76: =SUM(Calcs!D68:H68)+SUM(Calcs!D79:H79) -> 0 | F76: =IFERROR(SUM(K40,K18:K20,K51,K33:K35)/SUM($K$40:$N$40,$K$18:$M$20,$K$51:$N$51,$K$33:$N$35),0) -> 0 | G76: =IFERROR(SUM(L40,L18:L20,L51,L33:L35)/SUM($K$40:$N$40,$K$18:$M$20,$K$51:$N$51,$K$33:$N$35),0) -> 0 | H76: =IFERROR(SUM(M40,M18:M20,M51,M33:M35)/SUM($K$40:$N$40,$K$18:$M$20,$K$51:$N$51,$K$33:$N$35),0) -> 0 | I76: =IFERROR(SUM(N40,N18:N20,N51,N33:N35)/SUM($K$40:$N$40,$K$18:$M$20,$K$51:$N$51,$K$33:$N$35),0) -> 0 | K76: =F76*$D76 -> 0 | L76: =G76*$D76 -> 0 | M76: =H76*$D76 -> 0 | N76: =I76*$D76 -> 0
C77: PRM Care Giver's Checklist | D77: =SUM(Calcs!D69:H69)+SUM(Calcs!D80:H80) -> 0 | F77: =IFERROR(SUM(K41,K18:K20,K52,K33:K35)/SUM($K$41:$N$41,$K$18:$M$20,$K$52:$N$52,$K$33:$N$35),0) -> 0 | G77: =IFERROR(SUM(L41,L18:L20,L52,L33:L35)/SUM($K$41:$N$41,$K$18:$M$20,$K$52:$N$52,$K$33:$N$35),0) -> 0 | H77: =IFERROR(SUM(M41,M18:M20,M52,M33:M35)/SUM($K$41:$N$41,$K$18:$M$20,$K$52:$N$52,$K$33:$N$35),0) -> 0 | I77: =IFERROR(SUM(N41,N18:N20,N52,N33:N35)/SUM($K$41:$N$41,$K$18:$M$20,$K$52:$N$52,$K$33:$N$35),0) -> 0 | K77: =F77*$D77 -> 0 | L77: =G77*$D77 -> 0 | M77: =H77*$D77 -> 0 | N77: =I77*$D77 -> 0
C78: PRM Physician Risk and Credibility Adjusted Report | D78: =SUM(Calcs!D70:H70)+SUM(Calcs!D81:H81) -> 0 | F78: =IFERROR(SUM(K42,K53)/SUM($K42:$N42,$K53:$N53),0) -> 0 | G78: =IFERROR(SUM(L42,L53)/SUM($K42:$N42,$K53:$N53),0) -> 0 | H78: =IFERROR(SUM(M42,M53)/SUM($K42:$N42,$K53:$N53),0) -> 0 | I78: =IFERROR(SUM(N42,N53)/SUM($K42:$N42,$K53:$N53),0) -> 0 | K78: =F78*$D78 -> 0 | L78: =G78*$D78 -> 0 | M78: =H78*$D78 -> 0 | N78: =I78*$D78 -> 0
C79: PRM PCP Dashboard | D79: =SUM(Calcs!D71:H71)+SUM(Calcs!D82:H82) -> 0 | F79: =IFERROR(SUM(K43,K54)/SUM($K43:$N43,$K54:$N54),0) -> 0 | G79: =IFERROR(SUM(L43,L54)/SUM($K43:$N43,$K54:$N54),0) -> 0 | H79: =IFERROR(SUM(M43,M54)/SUM($K43:$N43,$K54:$N54),0) -> 0 | I79: =IFERROR(SUM(N43,N54)/SUM($K43:$N43,$K54:$N54),0) -> 0 | K79: =F79*$D79 -> 0 | L79: =G79*$D79 -> 0 | M79: =H79*$D79 -> 0 | N79: =I79*$D79 -> 0
C80: PRM Conditions to Consider Dashboards | D80: =SUM(Calcs!D72:H72)+SUM(Calcs!D83:H83) -> 0 | F80: =IFERROR(SUM(K44,K19,K55,K34)/SUM($K$44:$N$44,$K$19:$N$19,$K$55:$N$55,$K$34:$N$34),0) -> 0 | G80: =IFERROR(SUM(L44,L19,L55,L34)/SUM($K$44:$N$44,$K$19:$N$19,$K$55:$N$55,$K$34:$N$34),0) -> 0 | H80: =IFERROR(SUM(M44,M19,M55,M34)/SUM($K$44:$N$44,$K$19:$N$19,$K$55:$N$55,$K$34:$N$34),0) -> 0 | I80: =IFERROR(SUM(N44,N19,N55,N34)/SUM($K$44:$N$44,$K$19:$N$19,$K$55:$N$55,$K$34:$N$34),0) -> 0 | K80: =F80*$D80 -> 0 | L80: =G80*$D80 -> 0 | M80: =H80*$D80 -> 0 | N80: =I80*$D80 -> 0
C81: Patient Flow | D81: =SUM(Calcs!D73:H73)+SUM(Calcs!D84:H84) -> 0 | F81: =IFERROR(SUM(K45,K56)/SUM($K45:$N45,$K56:$N56),0) -> 0 | G81: =IFERROR(SUM(L45,L56)/SUM($K45:$N45,$K56:$N56),0) -> 0 | H81: =IFERROR(SUM(M45,M56)/SUM($K45:$N45,$K56:$N56),0) -> 0 | I81: =IFERROR(SUM(N45,N56)/SUM($K45:$N45,$K56:$N56),0) -> 0 | K81: =F81*$D81 -> 0 | L81: =G81*$D81 -> 0 | M81: =H81*$D81 -> 0 | N81: =I81*$D81 -> 0
C82: Datamart | D82: =IF(Inputs!$C$4 = "Yes", 0, SUM(Calcs!D74:H74)+SUM(Calcs!D85:H85)) -> 9600 | F82: =IFERROR(SUM(K46,K57)/SUM($K46:$N46,$K57:$N57),0) -> 0.1 | G82: =IFERROR(SUM(L46,L57)/SUM($K46:$N46,$K57:$N57),0) -> 0.9 | H82: =IFERROR(SUM(M46,M57)/SUM($K46:$N46,$K57:$N57),0) -> 0 | I82: =IFERROR(SUM(N46,N57)/SUM($K46:$N46,$K57:$N57),0) -> 0 | K82: =F82*$D82 -> 960 | L82: =G82*$D82 -> 8640 | M82: =H82*$D82 -> 0 | N82: =I82*$D82 -> 0

Sheet Outputs_Timeline
F1: =COUNTIF(F3:F94,">0") -> 36 | I1: Implementation Fee | P1: Monthly Fees | W1: Quarterly Invoices | AD1: MARA Pricing
B2: Month | D2: Price Inflation | E2: Price Freeze | F2: Price Multiplier | G2: MARA Multiplier | I2: Total | J2: NY | K2: PRM | L2: MI | N2: MARA Cost | P2: Total | Q2: NY | R2: PRM | S2: MARA Royalties | T2: MI Royalties | U2: Other Royalties | W2: Total | X2: NY | Y2: PRM | Z2: MI Royalties | AA2: Other Royalties | AD2: Population #1 | AE2: Population #2 | AF2: Population #3 | AG2: Population #4 | AH2: Population #5
B3: 42917 | D3: =1 -> 1 | E3: =IF(B3=Inputs!$C$1,D3,1) -> 1 | F3: =IF(AND(B3>=Inputs!$C$1,B3<EDATE(Inputs!$C$1,Inputs!$C$2)),E3,0) -> 0 | G3: =IF(AND(B3>=Inputs!$C$1,B3<EDATE(Inputs!$C$1,Inputs!$C$2)),(1+'MARA Prices'!$F$1)^IFERROR(DATEDIF('MARA Prices'!$F$2,B3,"Y")+1, 0),0) -> 0 | I3: =IF($B3=Inputs!$C$1,SUM(Outputs_Internal!$D$4, Outputs_Internal!$D$5),0)*$D3 -> 0 | J3: =IF($B3=Inputs!$C$1,SUM(Outputs_Internal!K$4, Outputs_Internal!K$5),0)*$D3 -> 0 | K3: =IF($B3=Inputs!$C$1,SUM(Outputs_Internal!L$4, Outputs_Internal!L$5),0)*$D3 -> 0 | L3: =IF($B3=Inputs!$C$1,SUM(Outputs_Internal!M$4, Outputs_Internal!$M$5),0)*$D3 -> 0 | N3: =SUM(AD3:AH3) -> 0 | P3: =$F3*Outputs_Internal!$D$64/12+N3 -> 0 | Q3: =$F3*Outputs_Internal!K$64/12+N3*'MARA Prices'!$F$5 -> 0 | R3: =$F3*Outputs_Internal!L$64/12+N3*'MARA Prices'!$F$6 -> 0 | S3: =N3*'MARA Prices'!$F$4 -> 0 | T3: =$F3*Outputs_Internal!M$64/12 -> 0 | U3: =$F3*Outputs_Internal!N$64/12 -> 0 | AD3: ='MARA Prices'!H$21*$G3 -> 0 | AE3: ='MARA Prices'!I$21*$G3 -> 0 | AF3: ='MARA Prices'!J$21*$G3 -> 0 | AG3: ='MARA Prices'!K$21*$G3 -> 0 | AH3: ='MARA Prices'!L$21*$G3 -> 0
B4: =EDATE(B3,1) -> 42948 | D4: =D3*IF(AND(MONTH(B4)=1,YEAR(B4)>=YEAR(Prices!$L$15)),1+Prices!$L$14,1) -> 1 | E4: =IF(B4=Inputs!$C$1,D4,E3) -> 1 | F4: =IF(AND(B4>=Inputs!$C$1,B4<EDATE(Inputs!$C$1,Inputs!$C$2)),E4,0) -> 0 | G4: =IF(AND(B4>=Inputs!$C$1,B4<EDATE(Inputs!$C$1,Inputs!$C$2)),(1+'MARA Prices'!$F$1)^IFERROR(DATEDIF('MARA Prices'!$F$2,B4,"Y")+1, 0),0) -> 0 | I4: =IF($B4=Inputs!$C$1,SUM(Outputs_Internal!$D$4, Outputs_Internal!$D$5),0)*$D4 -> 0 | J4: =IF($B4=Inputs!$C$1,SUM(Outputs_Internal!K$4, Outputs_Internal!K$5),0)*$D4 -> 0 | K4: =IF($B4=Inputs!$C$1,SUM(Outputs_Internal!L$4, Outputs_Internal!L$5),0)*$D4 -> 0 | L4: =IF($B4=Inputs!$C$1,SUM(Outputs_Internal!M$4, Outputs_Internal!$M$5),0)*$D4 -> 0 | N4: =SUM(AD4:AH4) -> 0 | P4: =$F4*Outputs_Internal!$D$64/12+N4 -> 0 | Q4: =$F4*Outputs_Internal!K$64/12+N4*'MARA Prices'!$F$5 -> 0 | R4: =$F4*Outputs_Internal!L$64/12+N4*'MARA Prices'!$F$6 -> 0 | S4: =N4*'MARA Prices'!$F$4 -> 0 | T4: =$F4*Outputs_Internal!M$64/12 -> 0 | U4: =$F4*Outputs_Internal!N$64/12 -> 0 | AD4: ='MARA Prices'!H$21*$G4 -> 0 | AE4: ='MARA Prices'!I$21*$G4 -> 0 | AF4: ='MARA Prices'!J$21*$G4 -> 0 | AG4: ='MARA Prices'!K$21*$G4 -> 0 | AH4: ='MARA Prices'!L$21*$G4 -> 0
B5: =EDATE(B4,1) -> 42979 | D5: =D4*IF(AND(MONTH(B5)=1,YEAR(B5)>=YEAR(Prices!$L$15)),1+Prices!$L$14,1) -> 1 | E5: =IF(B5=Inputs!$C$1,D5,E4) -> 1 | F5: =IF(AND(B5>=Inputs!$C$1,B5<EDATE(Inputs!$C$1,Inputs!$C$2)),E5,0) -> 0 | G5: =IF(AND(B5>=Inputs!$C$1,B5<EDATE(Inputs!$C$1,Inputs!$C$2)),(1+'MARA Prices'!$F$1)^IFERROR(DATEDIF('MARA Prices'!$F$2,B5,"Y")+1, 0),0) -> 0 | I5: =IF($B5=Inputs!$C$1,SUM(Outputs_Internal!$D$4, Outputs_Internal!$D$5),0)*$D5 -> 0 | J5: =IF($B5=Inputs!$C$1,SUM(Outputs_Internal!K$4, Outputs_Internal!K$5),0)*$D5 -> 0 | K5: =IF($B5=Inputs!$C$1,SUM(Outputs_Internal!L$4, Outputs_Internal!L$5),0)*$D5 -> 0 | L5: =IF($B5=Inputs!$C$1,SUM(Outputs_Internal!M$4, Outputs_Internal!$M$5),0)*$D5 -> 0 | N5: =SUM(AD5:AH5) -> 0 | P5: =$F5*Outputs_Internal!$D$64/12+N5 -> 0 | Q5: =$F5*Outputs_Internal!K$64/12+N5*'MARA Prices'!$F$5 -> 0 | R5: =$F5*Outputs_Internal!L$64/12+N5*'MARA Prices'!$F$6 -> 0 | S5: =N5*'MARA Prices'!$F$4 -> 0 | T5: =$F5*Outputs_Internal!M$64/12 -> 0 | U5: =$F5*Outputs_Internal!N$64/12 -> 0 | W5: =IF(MOD(MONTH($B5),3)=0,SUM(I3:I5,P3:P5),0) -> 0 | X5: =IF(MOD(MONTH($B5),3)=0,SUM(J3:J5,Q3:Q5),0) -> 0 | Y5: =IF(MOD(MONTH($B5),3)=0,SUM(K3:K5,R3:R5),0) -> 0 | Z5: =IF(MOD(MONTH($B5),3)=0,SUM(L3:L5,T3:T5),0) -> 0 | AA5: =IF(MOD(MONTH($B5),3)=0,SUM(U3:U5,S3:S5),0) -> 0 | AD5: ='MARA Prices'!H$21*$G5 -> 0 | AE5: ='MARA Prices'!I$21*$G5 -> 0 | AF5: ='MARA Prices'!J$21*$G5 -> 0 | AG5: ='MARA Prices'!K$21*$G5 -> 0 | AH5: ='MARA Prices'!L$21*$G5 -> 0
B6: =EDATE(B5,1) -> 43009 | D6: =D5*IF(AND(MONTH(B6)=1,YEAR(B6)>=YEAR(Prices!$L$15)),1+Prices!$L$14,1) -> 1 | E6: =IF(B6=Inputs!$C$1,D6,E5) -> 1 | F6: =IF(AND(B6>=Inputs!$C$1,B6<EDATE(Inputs!$C$1,Inputs!$C$2)),E6,0) -> 0 | G6: =IF(AND(B6>=Inputs!$C$1,B6<EDATE(Inputs!$C$1,Inputs!$C$2)),(1+'MARA Prices'!$F$1)^IFERROR(DATEDIF('MARA Prices'!$F$2,B6,"Y")+1, 0),0) -> 0 | I6: =IF($B6=Inputs!$C$1,SUM(Outputs_Internal!$D$4, Outputs_Internal!$D$5),0)*$D6 -> 0 | J6: =IF($B6=Inputs!$C$1,SUM(Outputs_Internal!K$4, Outputs_Internal!K$5),0)*$D6 -> 0 | K6: =IF($B6=Inputs!$C$1,SUM(Outputs_Internal!L$4, Outputs_Internal!L$5),0)*$D6 -> 0 | L6: =IF($B6=Inputs!$C$1,SUM(Outputs_Internal!M$4, Outputs_Internal!$M$5),0)*$D6 -> 0 | N6: =SUM(AD6:AH6) -> 0 | P6: =$F6*Outputs_Internal!$D$64/12+N6 -> 0 | Q6: =$F6*Outputs_Internal!K$64/12+N6*'MARA Prices'!$F$5 -> 0 | R6: =$F6*Outputs_Internal!L$64/12+N6*'MARA Prices'!$F$6 -> 0 | S6: =N6*'MARA Prices'!$F$4 -> 0 | T6: =$F6*Outputs_Internal!M$64/12 -> 0 | U6: =$F6*Outputs_Internal!N$64/12 -> 0 | W6: =IF(MOD(MONTH($B6),3)=0,SUM(I4:I6,P4:P6),0) -> 0 | X6: =IF(MOD(MONTH($B6),3)=0,SUM(J4:J6,Q4:Q6),0) -> 0 | Y6: =IF(MOD(MONTH($B6),3)=0,SUM(K4:K6,R4:R6),0) -> 0 | Z6: =IF(MOD(MONTH($B6),3)=0,SUM(L4:L6,T4:T6),0) -> 0 | AA6: =IF(MOD(MONTH($B6),3)=0,SUM(U4:U6,S4:S6),0) -> 0 | AD6: ='MARA Prices'!H$21*$G6 -> 0 | AE6: ='MARA Prices'!I$21*$G6 -> 0 | AF6: ='MARA Prices'!J$21*$G6 -> 0 | AG6: ='MARA Prices'!K$21*$G6 -> 0 | AH6: ='MARA Prices'!L$21*$G6 -> 0
B7: =EDATE(B6,1) -> 43040 | D7: =D6*IF(AND(MONTH(B7)=1,YEAR(B7)>=YEAR(Prices!$L$15)),1+Prices!$L$14,1) -> 1 | E7: =IF(B7=Inputs!$C$1,D7,E6) -> 1 | F7: =IF(AND(B7>=Inputs!$C$1,B7<EDATE(Inputs!$C$1,Inputs!$C$2)),E7,0) -> 0 | G7: =IF(AND(B7>=Inputs!$C$1,B7<EDATE(Inputs!$C$1,Inputs!$C$2)),(1+'MARA Prices'!$F$1)^IFERROR(DATEDIF('MARA Prices'!$F$2,B7,"Y")+1, 0),0) -> 0 | I7: =IF($B7=Inputs!$C$1,SUM(Outputs_Internal!$D$4, Outputs_Internal!$D$5),0)*$D7 -> 0 | J7: =IF($B7=Inputs!$C$1,SUM(Outputs_Internal!K$4, Outputs_Internal!K$5),0)*$D7 -> 0 | K7: =IF($B7=Inputs!$C$1,SUM(Outputs_Internal!L$4, Outputs_Internal!L$5),0)*$D7 -> 0 | L7: =IF($B7=Inputs!$C$1,SUM(Outputs_Internal!M$4, Outputs_Internal!$M$5),0)*$D7 -> 0 | N7: =SUM(AD7:AH7) -> 0 | P7: =$F7*Outputs_Internal!$D$64/12+N7 -> 0 | Q7: =$F7*Outputs_Internal!K$64/12+N7*'MARA Prices'!$F$5 -> 0 | R7: =$F7*Outputs_Internal!L$64/12+N7*'MARA Prices'!$F$6 -> 0 | S7: =N7*'MARA Prices'!$F$4 -> 0 | T7: =$F7*Outputs_Internal!M$64/12 -> 0 | U7: =$F7*Outputs_Internal!N$64/12 -> 0 | W7: =IF(MOD(MONTH($B7),3)=0,SUM(I5:I7,P5:P7),0) -> 0 | X7: =IF(MOD(MONTH($B7),3)=0,SUM(J5:J7,Q5:Q7),0) -> 0 | Y7: =IF(MOD(MONTH($B7),3)=0,SUM(K5:K7,R5:R7),0) -> 0 | Z7: =IF(MOD(MONTH($B7),3)=0,SUM(L5:L7,T5:T7),0) -> 0 | AA7: =IF(MOD(MONTH($B7),3)=0,SUM(U5:U7,S5:S7),0) -> 0 | AD7: ='MARA Prices'!H$21*$G7 -> 0 | AE7: ='MARA Prices'!I$21*$G7 -> 0 | AF7: ='MARA Prices'!J$21*$G7 -> 0 | AG7: ='MARA Prices'!K$21*$G7 -> 0 | AH7: ='MARA Prices'!L$21*$G7 -> 0
B8: =EDATE(B7,1) -> 43070 | D8: =D7*IF(AND(MONTH(B8)=1,YEAR(B8)>=YEAR(Prices!$L$15)),1+Prices!$L$14,1) -> 1 | E8: =IF(B8=Inputs!$C$1,D8,E7) -> 1 | F8: =IF(AND(B8>=Inputs!$C$1,B8<EDATE(Inputs!$C$1,Inputs!$C$2)),E8,0) -> 0 | G8: =IF(AND(B8>=Inputs!$C$1,B8<EDATE(Inputs!$C$1,Inputs!$C$2)),(1+'MARA Prices'!$F$1)^IFERROR(DATEDIF('MARA Prices'!$F$2,B8,"Y")+1, 0),0) -> 0 | I8: =IF($B8=Inputs!$C$1,SUM(Outputs_Internal!$D$4, Outputs_Internal!$D$5),0)*$D8 -> 0 | J8: =IF($B8=Inputs!$C$1,SUM(Outputs_Internal!K$4, Outputs_Internal!K$5),0)*$D8 -> 0 | K8: =IF($B8=Inputs!$C$1,SUM(Outputs_Internal!L$4, Outputs_Internal!L$5),0)*$D8 -> 0 | L8: =IF($B8=Inputs!$C$1,SUM(Outputs_Internal!M$4, Outputs_Internal!$M$5),0)*$D8 -> 0 | N8: =SUM(AD8:AH8) -> 0 | P8: =$F8*Outputs_Internal!$D$64/12+N8 -> 0 | Q8: =$F8*Outputs_Internal!K$64/12+N8*'MARA Prices'!$F$5 -> 0 | R8: =$F8*Outputs_Internal!L$64/12+N8*'MARA Prices'!$F$6 -> 0 | S8: =N8*'MARA Prices'!$F$4 -> 0 | T8: =$F8*Outputs_Internal!M$64/12 -> 0 | U8: =$F8*Outputs_Internal!N$64/12 -> 0 | W8: =IF(MOD(MONTH($B8),3)=0,SUM(I6:I8,P6:P8),0) -> 0 | X8: =IF(MOD(MONTH($B8),3)=0,SUM(J6:J8,Q6:Q8),0) -> 0 | Y8: =IF(MOD(MONTH($B8),3)=0,SUM(K6:K8,R6:R8),0) -> 0 | Z8: =IF(MOD(MONTH($B8),3)=0,SUM(L6:L8,T6:T8),0) -> 0 | AA8: =IF(MOD(MONTH($B8),3)=0,SUM(U6:U8,S6:S8),0) -> 0 | AD8: ='MARA Prices'!H$21*$G8 -> 0 | AE8: ='MARA Prices'!I$21*$G8 -> 0 | AF8: ='MARA Prices'!J$21*$G8 -> 0 | AG8: ='MARA Prices'!K$21*$G8 -> 0 | AH8: ='MARA Prices'!L$21*$G8 -> 0
B9: =EDATE(B8,1) -> 43101 | D9: =D8*IF(AND(MONTH(B9)=1,YEAR(B9)>=YEAR(Prices!$L$15)),1+Prices!$L$14,1) -> 1 | E9: =IF(B9=Inputs!$C$1,D9,E8) -> 1 | F9: =IF(AND(B9>=Inputs!$C$1,B9<EDATE(Inputs!$C$1,Inputs!$C$2)),E9,0) -> 0 | G9: =IF(AND(B9>=Inputs!$C$1,B9<EDATE(Inputs!$C$1,Inputs!$C$2)),(1+'MARA Prices'!$F$1)^IFERROR(DATEDIF('MARA Prices'!$F$2,B9,"Y")+1, 0),0) -> 0 | I9: =IF($B9=Inputs!$C$1,SUM(Outputs_Internal!$D$4, Outputs_Internal!$D$5),0)*$D9 -> 0 | J9: =IF($B9=Inputs!$C$1,SUM(Outputs_Internal!K$4, Outputs_Internal!K$5),0)*$D9 -> 0 | K9: =IF($B9=Inputs!$C$1,SUM(Outputs_Internal!L$4, Outputs_Internal!L$5),0)*$D9 -> 0 | L9: =IF($B9=Inputs!$C$1,SUM(Outputs_Internal!M$4, Outputs_Internal!$M$5),0)*$D9 -> 0 | N9: =SUM(AD9:AH9) -> 0 | P9: =$F9*Outputs_Internal!$D$64/12+N9 -> 0 | Q9: =$F9*Outputs_Internal!K$64/12+N9*'MARA Prices'!$F$5 -> 0 | R9: =$F9*Outputs_Internal!L$64/12+N9*'MARA Prices'!$F$6 -> 0 | S9: =N9*'MARA Prices'!$F$4 -> 0 | T9: =$F9*Outputs_Internal!M$64/12 -> 0 | U9: =$F9*Outputs_Internal!N$64/12 -> 0 | W9: =IF(MOD(MONTH($B9),3)=0,SUM(I7:I9,P7:P9),0) -> 0 | X9: =IF(MOD(MONTH($B9),3)=0,SUM(J7:J9,Q7:Q9),0) -> 0 | Y9: =IF(MOD(MONTH($B9),3)=0,SUM(K7:K9,R7:R9),0) -> 0 | Z9: =IF(MOD(MONTH($B9),3)=0,SUM(L7:L9,T7:T9),0) -> 0 | AA9: =IF(MOD(MONTH($B9),3)=0,SUM(U7:U9,S7:S9),0) -> 0 | AD9: ='MARA Prices'!H$21*$G9 -> 0 | AE9: ='MARA Prices'!I$21*$G9 -> 0 | AF9: ='MARA Prices'!J$21*$G9 -> 0 | AG9: ='MARA Prices'!K$21*$G9 -> 0 | AH9: ='MARA Prices'!L$21*$G9 -> 0
B10: =EDATE(B9,1) -> 43132 | D10: =D9*IF(AND(MONTH(B10)=1,YEAR(B10)>=YEAR(Prices!$L$15)),1+Prices!$L$14,1) -> 1 | E10: =IF(B10=Inputs!$C$1,D10,E9) -> 1 | F10: =IF(AND(B10>=Inputs!$C$1,B10<EDATE(Inputs!$C$1,Inputs!$C$2)),E10,0) -> 0 | G10: =IF(AND(B10>=Inputs!$C$1,B10<EDATE(Inputs!$C$1,Inputs!$C$2)),(1+'MARA Prices'!$F$1)^IFERROR(DATEDIF('MARA Prices'!$F$2,B10,"Y")+1, 0),0) -> 0 | I10: =IF($B10=Inputs!$C$1,SUM(Outputs_Internal!$D$4, Outputs_Internal!$D$5),0)*$D10 -> 0 | J10: =IF($B10=Inputs!$C$1,SUM(Outputs_Internal!K$4, Outputs_Internal!K$5),0)*$D10 -> 0 | K10: =IF($B10=Inputs!$C$1,SUM(Outputs_Internal!L$4, Outputs_Internal!L$5),0)*$D10 -> 0 | L10: =IF($B10=Inputs!$C$1,SUM(Outputs_Internal!M$4, Outputs_Internal!$M$5),0)*$D10 -> 0 | N10: =SUM(AD10:AH10) -> 0 | P10: =$F10*Outputs_Internal!$D$64/12+N10 -> 0 | Q10: =$F10*Outputs_Internal!K$64/12+N10*'MARA Prices'!$F$5 -> 0 | R10: =$F10*Outputs_Internal!L$64/12+N10*'MARA Prices'!$F$6 -> 0 | S10: =N10*'MARA Prices'!$F$4 -> 0 | T10: =$F10*Outputs_Internal!M$64/12 -> 0 | U10: =$F10*Outputs_Internal!N$64/12 -> 0 | W10: =IF(MOD(MONTH($B10),3)=0,SUM(I8:I10,P8:P10),0) -> 0 | X10: =IF(MOD(MONTH($B10),3)=0,SUM(J8:J10,Q8:Q10),0) -> 0 | Y10: =IF(MOD(MONTH($B10),3)=0,SUM(K8:K10,R8:R10),0) -> 0 | Z10: =IF(MOD(MONTH($B10),3)=0,SUM(L8:L10,T8:T10),0) -> 0 | AA10: =IF(MOD(MONTH($B10),3)=0,SUM(U8:U10,S8:S10),0) -> 0 | AD10: ='MARA Prices'!H$21*$G10 -> 0 | AE10: ='MARA Prices'!I$21*$G10 -> 0 | AF10: ='MARA Prices'!J$21*$G10 -> 0 | AG10: ='MARA Prices'!K$21*$G10 -> 0 | AH10: ='MARA Prices'!L$21*$G10 -> 0
B11: =EDATE(B10,1) -> 43160 | D11: =D10*IF(AND(MONTH(B11)=1,YEAR(B11)>=YEAR(Prices!$L$15)),1+Prices!$L$14,1) -> 1 | E11: =IF(B11=Inputs!$C$1,D11,E10) -> 1 | F11: =IF(AND(B11>=Inputs!$C$1,B11<EDATE(Inputs!$C$1,Inputs!$C$2)),E11,0) -> 0 | G11: =IF(AND(B11>=Inputs!$C$1,B11<EDATE(Inputs!$C$1,Inputs!$C$2)),(1+'MARA Prices'!$F$1)^IFERROR(DATEDIF('MARA Prices'!$F$2,B11,"Y")+1, 0),0) -> 0 | I11: =IF($B11=Inputs!$C$1,SUM(Outputs_Internal!$D$4, Outputs_Internal!$D$5),0)*$D11 -> 0 | J11: =IF($B11=Inputs!$C$1,SUM(Outputs_Internal!K$4, Outputs_Internal!K$5),0)*$D11 -> 0 | K11: =IF($B11=Inputs!$C$1,SUM(Outputs_Internal!L$4, Outputs_Internal!L$5),0)*$D11 -> 0 | L11: =IF($B11=Inputs!$C$1,SUM(Outputs_Internal!M$4, Outputs_Internal!$M$5),0)*$D11 -> 0 | N11: =SUM(AD11:AH11) -> 0 | P11: =$F11*Outputs_Internal!$D$64/12+N11 -> 0 | Q11: =$F11*Outputs_Internal!K$64/12+N11*'MARA Prices'!$F$5 -> 0 | R11: =$F11*Outputs_Internal!L$64/12+N11*'MARA Prices'!$F$6 -> 0 | S11: =N11*'MARA Prices'!$F$4 -> 0 | T11: =$F11*Outputs_Internal!M$64/12 -> 0 | U11: =$F11*Outputs_Internal!N$64/12 -> 0 | W11: =IF(MOD(MONTH($B11),3)=0,SUM(I9:I11,P9:P11),0) -> 0 | X11: =IF(MOD(MONTH($B11),3)=0,SUM(J9:J11,Q9:Q11),0) -> 0 | Y11: =IF(MOD(MONTH($B11),3)=0,SUM(K9:K11,R9:R11),0) -> 0 | Z11: =IF(MOD(MONTH($B11),3)=0,SUM(L9:L11,T9:T11),0) -> 0 | AA11: =IF(MOD(MONTH($B11),3)=0,SUM(U9:U11,S9:S11),0) -> 0 | AD11: ='MARA Prices'!H$21*$G11 -> 0 | AE11: ='MARA Prices'!I$21*$G11 -> 0 | AF11: ='MARA Prices'!J$21*$G11 -> 0 | AG11: ='MARA Prices'!K$21*$G11 -> 0 | AH11: ='MARA Prices'!L$21*$G11 -> 0
B12: =EDATE(B11,1) -> 43191 | D12: =D11*IF(AND(MONTH(B12)=1,YEAR(B12)>=YEAR(Prices!$L$15)),1+Prices!$L$14,1) -> 1 | E12: =IF(B12=Inputs!$C$1,D12,E11) -> 1 | F12: =IF(AND(B12>=Inputs!$C$1,B12<EDATE(Inputs!$C$1,Inputs!$C$2)),E12,0) -> 0 | G12: =IF(AND(B12>=Inputs!$C$1,B12<EDATE(Inputs!$C$1,Inputs!$C$2)),(1+'MARA Prices'!$F$1)^IFERROR(DATEDIF('MARA Prices'!$F$2,B12,"Y")+1, 0),0) -> 0 | I12: =IF($B12=Inputs!$C$1,SUM(Outputs_Internal!$D$4, Outputs_Internal!$D$5),0)*$D12 -> 0 | J12: =IF($B12=Inputs!$C$1,SUM(Outputs_Internal!K$4, Outputs_Internal!K$5),0)*$D12 -> 0 | K12: =IF($B12=Inputs!$C$1,SUM(Outputs_Internal!L$4, Outputs_Internal!L$5),0)*$D12 -> 0 | L12: =IF($B12=Inputs!$C$1,SUM(Outputs_Internal!M$4, Outputs_Internal!$M$5),0)*$D12 -> 0 | N12: =SUM(AD12:AH12) -> 0 | P12: =$F12*Outputs_Internal!$D$64/12+N12 -> 0 | Q12: =$F12*Outputs_Internal!K$64/12+N12*'MARA Prices'!$F$5 -> 0 | R12: =$F12*Outputs_Internal!L$64/12+N12*'MARA Prices'!$F$6 -> 0 | S12: =N12*'MARA Prices'!$F$4 -> 0 | T12: =$F12*Outputs_Internal!M$64/12 -> 0 | U12: =$F12*Outputs_Internal!N$64/12 -> 0 | W12: =IF(MOD(MONTH($B12),3)=0,SUM(I10:I12,P10:P12),0) -> 0 | X12: =IF(MOD(MONTH($B12),3)=0,SUM(J10:J12,Q10:Q12),0) -> 0 | Y12: =IF(MOD(MONTH($B12),3)=0,SUM(K10:K12,R10:R12),0) -> 0 | Z12: =IF(MOD(MONTH($B12),3)=0,SUM(L10:L12,T10:T12),0) -> 0 | AA12: =IF(MOD(MONTH($B12),3)=0,SUM(U10:U12,S10:S12),0) -> 0 | AD12: ='MARA Prices'!H$21*$G12 -> 0 | AE12: ='MARA Prices'!I$21*$G12 -> 0 | AF12: ='MARA Prices'!J$21*$G12 -> 0 | AG12: ='MARA Prices'!K$21*$G12 -> 0 | AH12: ='MARA Prices'!L$21*$G12 -> 0
B13: =EDATE(B12,1) -> 43221 | D13: =D12*IF(AND(MONTH(B13)=1,YEAR(B13)>=YEAR(Prices!$L$15)),1+Prices!$L$14,1) -> 1 | E13: =IF(B13=Inputs!$C$1,D13,E12) -> 1 | F13: =IF(AND(B13>=Inputs!$C$1,B13<EDATE(Inputs!$C$1,Inputs!$C$2)),E13,0) -> 0 | G13: =IF(AND(B13>=Inputs!$C$1,B13<EDATE(Inputs!$C$1,Inputs!$C$2)),(1+'MARA Prices'!$F$1)^IFERROR(DATEDIF('MARA Prices'!$F$2,B13,"Y")+1, 0),0) -> 0 | I13: =IF($B13=Inputs!$C$1,SUM(Outputs_Internal!$D$4, Outputs_Internal!$D$5),0)*$D13 -> 0 | J13: =IF($B13=Inputs!$C$1,SUM(Outputs_Internal!K$4, Outputs_Internal!K$5),0)*$D13 -> 0 | K13: =IF($B13=Inputs!$C$1,SUM(Outputs_Internal!L$4, Outputs_Internal!L$5),0)*$D13 -> 0 | L13: =IF($B13=Inputs!$C$1,SUM(Outputs_Internal!M$4, Outputs_Internal!$M$5),0)*$D13 -> 0 | N13: =SUM(AD13:AH13) -> 0 | P13: =$F13*Outputs_Internal!$D$64/12+N13 -> 0 | Q13: =$F13*Outputs_Internal!K$64/12+N13*'MARA Prices'!$F$5 -> 0 | R13: =$F13*Outputs_Internal!L$64/12+N13*'MARA Prices'!$F$6 -> 0 | S13: =N13*'MARA Prices'!$F$4 -> 0 | T13: =$F13*Outputs_Internal!M$64/12 -> 0 | U13: =$F13*Outputs_Internal!N$64/12 -> 0 | W13: =IF(MOD(MONTH($B13),3)=0,SUM(I11:I13,P11:P13),0) -> 0 | X13: =IF(MOD(MONTH($B13),3)=0,SUM(J11:J13,Q11:Q13),0) -> 0 | Y13: =IF(MOD(MONTH($B13),3)=0,SUM(K11:K13,R11:R13),0) -> 0 | Z13: =IF(MOD(MONTH($B13),3)=0,SUM(L11:L13,T11:T13),0) -> 0 | AA13: =IF(MOD(MONTH($B13),3)=0,SUM(U11:U13,S11:S13),0) -> 0 | AD13: ='MARA Prices'!H$21*$G13 -> 0 | AE13: ='MARA Prices'!I$21*$G13 -> 0 | AF13: ='MARA Prices'!J$21*$G13 -> 0 | AG13: ='MARA Prices'!K$21*$G13 -> 0 | AH13: ='MARA Prices'!L$21*$G13 -> 0
B14: =EDATE(B13,1) -> 43252 | D14: =D13*IF(AND(MONTH(B14)=1,YEAR(B14)>=YEAR(Prices!$L$15)),1+Prices!$L$14,1) -> 1 | E14: =IF(B14=Inputs!$C$1,D14,E13) -> 1 | F14: =IF(AND(B14>=Inputs!$C$1,B14<EDATE(Inputs!$C$1,Inputs!$C$2)),E14,0) -> 0 | G14: =IF(AND(B14>=Inputs!$C$1,B14<EDATE(Inputs!$C$1,Inputs!$C$2)),(1+'MARA Prices'!$F$1)^IFERROR(DATEDIF('MARA Prices'!$F$2,B14,"Y")+1, 0),0) -> 0 | I14: =IF($B14=Inputs!$C$1,SUM(Outputs_Internal!$D$4, Outputs_Internal!$D$5),0)*$D14 -> 0 | J14: =IF($B14=Inputs!$C$1,SUM(Outputs_Internal!K$4, Outputs_Internal!K$5),0)*$D14 -> 0 | K14: =IF($B14=Inputs!$C$1,SUM(Outputs_Internal!L$4, Outputs_Internal!L$5),0)*$D14 -> 0 | L14: =IF($B14=Inputs!$C$1,SUM(Outputs_Internal!M$4, Outputs_Internal!$M$5),0)*$D14 -> 0 | N14: =SUM(AD14:AH14) -> 0 | P14: =$F14*Outputs_Internal!$D$64/12+N14 -> 0 | Q14: =$F14*Outputs_Internal!K$64/12+N14*'MARA Prices'!$F$5 -> 0 | R14: =$F14*Outputs_Internal!L$64/12+N14*'MARA Prices'!$F$6 -> 0 | S14: =N14*'MARA Prices'!$F$4 -> 0 | T14: =$F14*Outputs_Internal!M$64/12 -> 0 | U14: =$F14*Outputs_Internal!N$64/12 -> 0 | W14: =IF(MOD(MONTH($B14),3)=0,SUM(I12:I14,P12:P14),0) -> 0 | X14: =IF(MOD(MONTH($B14),3)=0,SUM(J12:J14,Q12:Q14),0) -> 0 | Y14: =IF(MOD(MONTH($B14),3)=0,SUM(K12:K14,R12:R14),0) -> 0 | Z14: =IF(MOD(MONTH($B14),3)=0,SUM(L12:L14,T12:T14),0) -> 0 | AA14: =IF(MOD(MONTH($B14),3)=0,SUM(U12:U14,S12:S14),0) -> 0 | AD14: ='MARA Prices'!H$21*$G14 -> 0 | AE14: ='MARA Prices'!I$21*$G14 -> 0 | AF14: ='MARA Prices'!J$21*$G14 -> 0 | AG14: ='MARA Prices'!K$21*$G14 -> 0 | AH14: ='MARA Prices'!L$21*$G14 -> 0
B15: =EDATE(B14,1) -> 43282 | D15: =D14*IF(AND(MONTH(B15)=1,YEAR(B15)>=YEAR(Prices!$L$15)),1+Prices!$L$14,1) -> 1 | E15: =IF(B15=Inputs!$C$1,D15,E14) -> 1 | F15: =IF(AND(B15>=Inputs!$C$1,B15<EDATE(Inputs!$C$1,Inputs!$C$2)),E15,0) -> 0 | G15: =IF(AND(B15>=Inputs!$C$1,B15<EDATE(Inputs!$C$1,Inputs!$C$2)),(1+'MARA Prices'!$F$1)^IFERROR(DATEDIF('MARA Prices'!$F$2,B15,"Y")+1, 0),0) -> 0 | I15: =IF($B15=Inputs!$C$1,SUM(Outputs_Internal!$D$4, Outputs_Internal!$D$5),0)*$D15 -> 0 | J15: =IF($B15=Inputs!$C$1,SUM(Outputs_Internal!K$4, Outputs_Internal!K$5),0)*$D15 -> 0 | K15: =IF($B15=Inputs!$C$1,SUM(Outputs_Internal!L$4, Outputs_Internal!L$5),0)*$D15 -> 0 | L15: =IF($B15=Inputs!$C$1,SUM(Outputs_Internal!M$4, Outputs_Internal!$M$5),0)*$D15 -> 0 | N15: =SUM(AD15:AH15) -> 0 | P15: =$F15*Outputs_Internal!$D$64/12+N15 -> 0 | Q15: =$F15*Outputs_Internal!K$64/12+N15*'MARA Prices'!$F$5 -> 0 | R15: =$F15*Outputs_Internal!L$64/12+N15*'MARA Prices'!$F$6 -> 0 | S15: =N15*'MARA Prices'!$F$4 -> 0 | T15: =$F15*Outputs_Internal!M$64/12 -> 0 | U15: =$F15*Outputs_Internal!N$64/12 -> 0 | W15: =IF(MOD(MONTH($B15),3)=0,SUM(I13:I15,P13:P15),0) -> 0 | X15: =IF(MOD(MONTH($B15),3)=0,SUM(J13:J15,Q13:Q15),0) -> 0 | Y15: =IF(MOD(MONTH($B15),3)=0,SUM(K13:K15,R13:R15),0) -> 0 | Z15: =IF(MOD(MONTH($B15),3)=0,SUM(L13:L15,T13:T15),0) -> 0 | AA15: =IF(MOD(MONTH($B15),3)=0,SUM(U13:U15,S13:S15),0) -> 0 | AD15: ='MARA Prices'!H$21*$G15 -> 0 | AE15: ='MARA Prices'!I$21*$G15 -> 0 | AF15: ='MARA Prices'!J$21*$G15 -> 0 | AG15: ='MARA Prices'!K$21*$G15 -> 0 | AH15: ='MARA Prices'!L$21*$G15 -> 0
B16: =EDATE(B15,1) -> 43313 | D16: =D15*IF(AND(MONTH(B16)=1,YEAR(B16)>=YEAR(Prices!$L$15)),1+Prices!$L$14,1) -> 1 | E16: =IF(B16=Inputs!$C$1,D16,E15) -> 1 | F16: =IF(AND(B16>=Inputs!$C$1,B16<EDATE(Inputs!$C$1,Inputs!$C$2)),E16,0) -> 0 | G16: =IF(AND(B16>=Inputs!$C$1,B16<EDATE(Inputs!$C$1,Inputs!$C$2)),(1+'MARA Prices'!$F$1)^IFERROR(DATEDIF('MARA Prices'!$F$2,B16,"Y")+1, 0),0) -> 0 | I16: =IF($B16=Inputs!$C$1,SUM(Outputs_Internal!$D$4, Outputs_Internal!$D$5),0)*$D16 -> 0 | J16: =IF($B16=Inputs!$C$1,SUM(Outputs_Internal!K$4, Outputs_Internal!K$5),0)*$D16 -> 0 | K16: =IF($B16=Inputs!$C$1,SUM(Outputs_Internal!L$4, Outputs_Internal!L$5),0)*$D16 -> 0 | L16: =IF($B16=Inputs!$C$1,SUM(Outputs_Internal!M$4, Outputs_Internal!$M$5),0)*$D16 -> 0 | N16: =SUM(AD16:AH16) -> 0 | P16: =$F16*Outputs_Internal!$D$64/12+N16 -> 0 | Q16: =$F16*Outputs_Internal!K$64/12+N16*'MARA Prices'!$F$5 -> 0 | R16: =$F16*Outputs_Internal!L$64/12+N16*'MARA Prices'!$F$6 -> 0 | S16: =N16*'MARA Prices'!$F$4 -> 0 | T16: =$F16*Outputs_Internal!M$64/12 -> 0 | U16: =$F16*Outputs_Internal!N$64/12 -> 0 | W16: =IF(MOD(MONTH($B16),3)=0,SUM(I14:I16,P14:P16),0) -> 0 | X16: =IF(MOD(MONTH($B16),3)=0,SUM(J14:J16,Q14:Q16),0) -> 0 | Y16: =IF(MOD(MONTH($B16),3)=0,SUM(K14:K16,R14:R16),0) -> 0 | Z16: =IF(MOD(MONTH($B16),3)=0,SUM(L14:L16,T14:T16),0) -> 0 | AA16: =IF(MOD(MONTH($B16),3)=0,SUM(U14:U16,S14:S16),0) -> 0 | AD16: ='MARA Prices'!H$21*$G16 -> 0 | AE16: ='MARA Prices'!I$21*$G16 -> 0 | AF16: ='MARA Prices'!J$21*$G16 -> 0 | AG16: ='MARA Prices'!K$21*$G16 -> 0 | AH16: ='MARA Prices'!L$21*$G16 -> 0
... B94: =EDATE(B93,1) -> 45689 | D94: =D93*IF(AND(MONTH(B94)=1,YEAR(B94)>=YEAR(Prices!$L$15)),1+Prices!$L$14,1) -> 1.0908505 | E94: =IF(B94=Inputs!$C$1,D94,E93) -> 1.0125 | F94: =IF(AND(B94>=Inputs!$C$1,B94<EDATE(Inputs!$C$1,Inputs!$C$2)),E94,0) -> 0 | G94: =IF(AND(B94>=Inputs!$C$1,B94<EDATE(Inputs!$C$1,Inputs!$C$2)),(1+'MARA Prices'!$F$1)^IFERROR(DATEDIF('MARA Prices'!$F$2,B94,"Y")+1, 0),0) -> 0 | I94: =IF($B94=Inputs!$C$1,SUM(Outputs_Internal!$D$4, Outputs_Internal!$D$5),0)*$D94 -> 0 | J94: =IF($B94=Inputs!$C$1,SUM(Outputs_Internal!K$4, Outputs_Internal!K$5),0)*$D94 -> 0 | K94: =IF($B94=Inputs!$C$1,SUM(Outputs_Internal!L$4, Outputs_Internal!L$5),0)*$D94 -> 0 | L94: =IF($B94=Inputs!$C$1,SUM(Outputs_Internal!M$4, Outputs_Internal!$M$5),0)*$D94 -> 0 | N94: =SUM(AD94:AH94) -> 0 | P94: =$F94*Outputs_Internal!$D$64/12+N94 -> 0 | Q94: =$F94*Outputs_Internal!K$64/12+N94*'MARA Prices'!$F$5 -> 0 | R94: =$F94*Outputs_Internal!L$64/12+N94*'MARA Prices'!$F$6 -> 0 | S94: =N94*'MARA Prices'!$F$4 -> 0 | T94: =$F94*Outputs_Internal!M$64/12 -> 0 | U94: =$F94*Outputs_Internal!N$64/12 -> 0 | W94: =IF(MOD(MONTH($B94),3)=0,SUM(I92:I94,P92:P94),0) -> 0 | X94: =IF(MOD(MONTH($B94),3)=0,SUM(J92:J94,Q92:Q94),0) -> 0 | Y94: =IF(MOD(MONTH($B94),3)=0,SUM(K92:K94,R92:R94),0) -> 0 | Z94: =IF(MOD(MONTH($B94),3)=0,SUM(L92:L94,T92:T94),0) -> 0 | AA94: =IF(MOD(MONTH($B94),3)=0,SUM(U92:U94,S92:S94),0) -> 0 | AD94: ='MARA Prices'!H$21*$G94 -> 0 | AE94: ='MARA Prices'!I$21*$G94 -> 0 | AF94: ='MARA Prices'!J$21*$G94 -> 0 | AG94: ='MARA Prices'!K$21*$G94 -> 0 | AH94: ='MARA Prices'!L$21*$G94 -> 0

Sheet Calcs
D2: Population #1 | E2: Population #2 | F2: Population #3 | G2: Population #4 | H2: Population #5 | K2: Product Ranking #1 | L2: Product Ranking #2 | M2: Product Ranking #3 | N2: Product Ranking #4 | O2: Product Ranking #5
B3: One-Time Fees:
C4: Implementation | D4: =IF(AND(Inputs!D8="Y",Inputs!D7="Y"), 0, IF(Inputs!D7="Y", SUM(Prices!$C$3, IF(Inputs!D$9 ="Y", Prices!$C$4, 0)), IF(Inputs!D7="N", Prices!$D$3, 0)))*Inputs!D12 -> 5000 | E4: =IF(AND(Inputs!E8="Y",Inputs!E7="Y"), 0, IF(Inputs!E7="Y", SUM(Prices!$C$3, IF(Inputs!E$9 ="Y", Prices!$C$4, 0)), IF(Inputs!E7="N", Prices!$D$3, 0)))*Inputs!E12 -> 0 | F4: =IF(AND(Inputs!F8="Y",Inputs!F7="Y"), 0, IF(Inputs!F7="Y", SUM(Prices!$C$3, IF(Inputs!F$9 ="Y", Prices!$C$4, 0)), IF(Inputs!F7="N", Prices!$D$3, 0)))*Inputs!F12 -> 0 | G4: =IF(AND(Inputs!G8="Y",Inputs!G7="Y"), 0, IF(Inputs!G7="Y", SUM(Prices!$C$3, IF(Inputs!G$9 ="Y", Prices!$C$4, 0)), IF(Inputs!G7="N", Prices!$D$3, 0)))*Inputs!G12 -> 0 | H4: =IF(AND(Inputs!H8="Y",Inputs!H7="Y"), 0, IF(Inputs!H7="Y", SUM(Prices!$C$3, IF(Inputs!H$9 ="Y", Prices!$C$4, 0)), IF(Inputs!H7="N", Prices!$D$3, 0)))*Inputs!H12 -> 0
K5: Lives Bottom | L5: Lives Top | M5: Scalar
B6: Patients 25k-50k (Non-CCLF Only) | D6: =IF(Inputs!D$7="N",MIN(MAX(Inputs!D$11-$K6,0),$L6-$K6),0) -> 0 | E6: =IF(Inputs!E$7="N",MIN(MAX(Inputs!E$11-$K6,0),$L6-$K6),0) -> 0 | F6: =IF(Inputs!F$7="N",MIN(MAX(Inputs!F$11-$K6,0),$L6-$K6),0) -> 0 | G6: =IF(Inputs!G$7="N",MIN(MAX(Inputs!G$11-$K6,0),$L6-$K6),0) -> 0 | H6: =IF(Inputs!H$7="N",MIN(MAX(Inputs!H$11-$K6,0),$L6-$K6),0) -> 0 | K6: 25000 | L6: 50000 | M6: 1
B7: Patients 50k-100k (Non-CCLF Only) | D7: =IF(Inputs!D$7="N",MIN(MAX(Inputs!D$11-$K7,0),$L7-$K7),0) -> 0 | E7: =IF(Inputs!E$7="N",MIN(MAX(Inputs!E$11-$K7,0),$L7-$K7),0) -> 0 | F7: =IF(Inputs!F$7="N",MIN(MAX(Inputs!F$11-$K7,0),$L7-$K7),0) -> 0 | G7: =IF(Inputs!G$7="N",MIN(MAX(Inputs!G$11-$K7,0),$L7-$K7),0) -> 0 | H7: =IF(Inputs!H$7="N",MIN(MAX(Inputs!H$11-$K7,0),$L7-$K7),0) -> 0 | K7: 50000 | L7: 100000 | M7: =Prices!$F$4 -> 0.6
B8: Patients 100k-250k (Non-CCLF Only) | D8: =IF(Inputs!D$7="N",MIN(MAX(Inputs!D$11-$K8,0),$L8-$K8),0) -> 0 | E8: =IF(Inputs!E$7="N",MIN(MAX(Inputs!E$11-$K8,0),$L8-$K8),0) -> 0 | F8: =IF(Inputs!F$7="N",MIN(MAX(Inputs!F$11-$K8,0),$L8-$K8),0) -> 0 | G8: =IF(Inputs!G$7="N",MIN(MAX(Inputs!G$11-$K8,0),$L8-$K8),0) -> 0 | H8: =IF(Inputs!H$7="N",MIN(MAX(Inputs!H$11-$K8,0),$L8-$K8),0) -> 0 | K8: 100000 | L8: 250000 | M8: =Prices!$G$4 -> 0.24
B9: Patients 250k+ (Non-CCLF Only) | D9: =IF(Inputs!D$7="N",MIN(MAX(Inputs!D$11-$K9,0),$L9-$K9),0) -> 0 | E9: =IF(Inputs!E$7="N",MIN(MAX(Inputs!E$11-$K9,0),$L9-$K9),0) -> 0 | F9: =IF(Inputs!F$7="N",MIN(MAX(Inputs!F$11-$K9,0),$L9-$K9),0) -> 0 | G9: =IF(Inputs!G$7="N",MIN(MAX(Inputs!G$11-$K9,0),$L9-$K9),0) -> 0 | H9: =IF(Inputs!H$7="N",MIN(MAX(Inputs!H$11-$K9,0),$L9-$K9),0) -> 0 | K9: 250000 | L9: 1000000000 | M9: =Prices!$H$4 -> 0.2
C10: Composite % Scalar of 25k-50k PMPM | D10: =IFERROR(SUMPRODUCT(D6:D9,$M$6:$M$9)/SUM(D6:D9),0) -> 0 | E10: =IFERROR(SUMPRODUCT(E6:E9,$M$6:$M$9)/SUM(E6:E9),0) -> 0 | F10: =IFERROR(SUMPRODUCT(F6:F9,$M$6:$M$9)/SUM(F6:F9),0) -> 0 | G10: =IFERROR(SUMPRODUCT(G6:G9,$M$6:$M$9)/SUM(G6:G9),0) -> 0 | H10: =IFERROR(SUMPRODUCT(H6:H9,$M$6:$M$9)/SUM(H6:H9),0) -> 0
C11: Total lives over 25k | D11: =SUM(D6:D9) -> 0 | E11: =SUM(E6:E9) -> 0 | F11: =SUM(F6:F9) -> 0 | G11: =SUM(G6:G9) -> 0 | H11: =SUM(H6:H9) -> 0
B13: Annual Base Data Fees (With Implicit forces):
C14: Base Processing Fee | D14: =IF(Inputs!D7="Y", Prices!$C$6, IF(Inputs!D7="N", Prices!$D$6, 0)) -> 15000 | E14: =IF(Inputs!E7="Y", Prices!$C$6, IF(Inputs!E7="N", Prices!$D$6, 0)) -> 0 | F14: =IF(Inputs!F7="Y", Prices!$C$6, IF(Inputs!F7="N", Prices!$D$6, 0)) -> 0 | G14: =IF(Inputs!G7="Y", Prices!$C$6, IF(Inputs!G7="N", Prices!$D$6, 0)) -> 0 | H14: =IF(Inputs!H7="Y", Prices!$C$6, IF(Inputs!H7="N", Prices!$D$6, 0)) -> 0
C15: HCC Risk Scores | D15: =IF(OR(Inputs!D14="Y",Inputs!D$24="Y"), Prices!$C10, 0) -> 1000 | E15: =IF(OR(Inputs!E14="Y",Inputs!E$24="Y"), Prices!$C10, 0) -> 0 | F15: =IF(OR(Inputs!F14="Y",Inputs!F$24="Y"), Prices!$C10, 0) -> 0 | G15: =IF(OR(Inputs!G14="Y",Inputs!G$24="Y"), Prices!$C10, 0) -> 0 | H15: =IF(OR(Inputs!H14="Y",Inputs!H$24="Y"), Prices!$C10, 0) -> 0
C16: HCG Benchmarks | D16: =IF(OR(Inputs!D15="Y",Inputs!D$24="Y"), Prices!$C11, 0) -> 4000 | E16: =IF(OR(Inputs!E15="Y",Inputs!E$24="Y"), Prices!$C11, 0) -> 0 | F16: =IF(OR(Inputs!F15="Y",Inputs!F$24="Y"), Prices!$C11, 0) -> 0 | G16: =IF(OR(Inputs!G15="Y",Inputs!G$24="Y"), Prices!$C11, 0) -> 0 | H16: =IF(OR(Inputs!H15="Y",Inputs!H$24="Y"), Prices!$C11, 0) -> 0
C17: PAC/Grouping/Benchmarks | D17: =IF(OR(Inputs!D16="Y",Inputs!D$24="Y"), Prices!$C12, 0) -> 2000 | E17: =IF(OR(Inputs!E16="Y",Inputs!E$24="Y"), Prices!$C12, 0) -> 0 | F17: =IF(OR(Inputs!F16="Y",Inputs!F$24="Y"), Prices!$C12, 0) -> 0 | G17: =IF(OR(Inputs!G16="Y",Inputs!G$24="Y"), Prices!$C12, 0) -> 0 | H17: =IF(OR(Inputs!H16="Y",Inputs!H$24="Y"), Prices!$C12, 0) -> 0
C18: Key Claims Metrics | D18: =IF(OR(Inputs!D17="Y",Inputs!D$24="Y"), Prices!$C13, 0) -> 2000 | E18: =IF(OR(Inputs!E17="Y",Inputs!E$24="Y"), Prices!$C13, 0) -> 0 | F18: =IF(OR(Inputs!F17="Y",Inputs!F$24="Y"), Prices!$C13, 0) -> 0 | G18: =IF(OR(Inputs!G17="Y",Inputs!G$24="Y"), Prices!$C13, 0) -> 0 | H18: =IF(OR(Inputs!H17="Y",Inputs!H$24="Y"), Prices!$C13, 0) -> 0
C19: Waste Calculator | D19: =IF(Inputs!D18="Y", Prices!$C14, 0) -> 6000 | E19: =IF(Inputs!E18="Y", Prices!$C14, 0) -> 0 | F19: =IF(Inputs!F18="Y", Prices!$C14, 0) -> 0 | G19: =IF(Inputs!G18="Y", Prices!$C14, 0) -> 0 | H19: =IF(Inputs!H18="Y", Prices!$C14, 0) -> 0
C20: Medical Conditions | D20: =IF(OR(Inputs!D19="Y",Inputs!D$24="Y"), Prices!$C15, 0) -> 4000 | E20: =IF(OR(Inputs!E19="Y",Inputs!E$24="Y"), Prices!$C15, 0) -> 0 | F20: =IF(OR(Inputs!F19="Y",Inputs!F$24="Y"), Prices!$C15, 0) -> 0 | G20: =IF(OR(Inputs!G19="Y",Inputs!G$24="Y"), Prices!$C15, 0) -> 0 | H20: =IF(OR(Inputs!H19="Y",Inputs!H$24="Y"), Prices!$C15, 0) -> 0
C21: Quality Measures | D21: =IF(Inputs!D22="Y",Prices!$C16, 0) -> 0 | E21: =IF(Inputs!E22="Y",Prices!$C16, 0) -> 0 | F21: =IF(Inputs!F22="Y",Prices!$C16, 0) -> 0 | G21: =IF(Inputs!G22="Y",Prices!$C16, 0) -> 0 | H21: =IF(Inputs!H22="Y",Prices!$C16, 0) -> 0
C22: PRM Oppourtunity Prospective Scores | D22: =IF(OR(Inputs!D20="Y",Inputs!D$25="Y",Inputs!D$26="Y"), Prices!$C17, 0) -> 0 | E22: =IF(OR(Inputs!E20="Y",Inputs!E$25="Y",Inputs!E$26="Y"), Prices!$C17, 0) -> 0 | F22: =IF(OR(Inputs!F20="Y",Inputs!F$25="Y",Inputs!F$26="Y"), Prices!$C17, 0) -> 0 | G22: =IF(OR(Inputs!G20="Y",Inputs!G$25="Y",Inputs!G$26="Y"), Prices!$C17, 0) -> 0 | H22: =IF(OR(Inputs!H20="Y",Inputs!H$25="Y",Inputs!H$26="Y"), Prices!$C17, 0) -> 0
C23: PRM Conditions to Consider (Data Only) | D23: =IF(OR(Inputs!D21="Y",Inputs!D$25="Y",Inputs!D$26="Y",Inputs!D$29="Y"), Prices!$C18, 0) -> 0 | E23: =IF(OR(Inputs!E21="Y",Inputs!E$25="Y",Inputs!E$26="Y",Inputs!E$29="Y"), Prices!$C18, 0) -> 0 | F23: =IF(OR(Inputs!F21="Y",Inputs!F$25="Y",Inputs!F$26="Y",Inputs!F$29="Y"), Prices!$C18, 0) -> 0 | G23: =IF(OR(Inputs!G21="Y",Inputs!G$25="Y",Inputs!G$26="Y",Inputs!G$29="Y"), Prices!$C18, 0) -> 0 | H23: =IF(OR(Inputs!H21="Y",Inputs!H$25="Y",Inputs!H$26="Y",Inputs!H$29="Y"), Prices!$C18, 0) -> 0
C24: PRM Medicare ACO Assignment (CCLF Only) | D24: =IF(Inputs!D$7="N",0, IF(OR(Inputs!D22="Y",Inputs!D$25="Y",Inputs!D$26="Y"), Prices!$C19, 0)) -> 0 | E24: =IF(Inputs!E$7="N",0, IF(OR(Inputs!E22="Y",Inputs!E$25="Y",Inputs!E$26="Y"), Prices!$C19, 0)) -> 0 | F24: =IF(Inputs!F$7="N",0, IF(OR(Inputs!F22="Y",Inputs!F$25="Y",Inputs!F$26="Y"), Prices!$C19, 0)) -> 0 | G24: =IF(Inputs!G$7="N",0, IF(OR(Inputs!G22="Y",Inputs!G$25="Y",Inputs!G$26="Y"), Prices!$C19, 0)) -> 0 | H24: =IF(Inputs!H$7="N",0, IF(OR(Inputs!H22="Y",Inputs!H$25="Y",Inputs!H$26="Y"), Prices!$C19, 0)) -> 0
B26: Annual PMPM Add-On Data Fees (With implicit forces):
C27: Base Processing Fee | D27: =IF(Inputs!D$7="Y", 0, IF(D$11 = "", "", PRODUCT(D$11, Prices!$E$6)))*D$10 -> 0 | E27: =IF(Inputs!E$7="Y", 0, IF(E$11 = "", "", PRODUCT(E$11, Prices!$E$6)))*E$10 -> 0 | F27: =IF(Inputs!F$7="Y", 0, IF(F$11 = "", "", PRODUCT(F$11, Prices!$E$6)))*F$10 -> 0 | G27: =IF(Inputs!G$7="Y", 0, IF(G$11 = "", "", PRODUCT(G$11, Prices!$E$6)))*G$10 -> 0 | H27: =IF(Inputs!H$7="Y", 0, IF(H$11 = "", "", PRODUCT(H$11, Prices!$E$6)))*H$10 -> 0
C28: HCC Risk Scores | D28: =IF(OR(Inputs!D$7="Y", D$11 = 0), 0, IF(OR(Inputs!D14="Y",Inputs!D$24="Y"),PRODUCT(D$11, Prices!$E10),0))*D$10 -> 0 | E28: =IF(OR(Inputs!E$7="Y", E$11 = 0), 0, IF(OR(Inputs!E14="Y",Inputs!E$24="Y"),PRODUCT(E$11, Prices!$E10),0))*E$10 -> 0 | F28: =IF(OR(Inputs!F$7="Y", F$11 = 0), 0, IF(OR(Inputs!F14="Y",Inputs!F$24="Y"),PRODUCT(F$11, Prices!$E10),0))*F$10 -> 0 | G28: =IF(OR(Inputs!G$7="Y", G$11 = 0), 0, IF(OR(Inputs!G14="Y",Inputs!G$24="Y"),PRODUCT(G$11, Prices!$E10),0))*G$10 -> 0 | H28: =IF(OR(Inputs!H$7="Y", H$11 = 0), 0, IF(OR(Inputs!H14="Y",Inputs!H$24="Y"),PRODUCT(H$11, Prices!$E10),0))*H$10 -> 0
C29: HCG Benchmarks | D29: =IF(OR(Inputs!D$7="Y", D$11 = 0), 0, IF(OR(Inputs!D15="Y",Inputs!D$24="Y"),PRODUCT(D$11, Prices!$E11),0))*D$10 -> 0 | E29: =IF(OR(Inputs!E$7="Y", E$11 = 0), 0, IF(OR(Inputs!E15="Y",Inputs!E$24="Y"),PRODUCT(E$11, Prices!$E11),0))*E$10 -> 0 | F29: =IF(OR(Inputs!F$7="Y", F$11 = 0), 0, IF(OR(Inputs!F15="Y",Inputs!F$24="Y"),PRODUCT(F$11, Prices!$E11),0))*F$10 -> 0 | G29: =IF(OR(Inputs!G$7="Y", G$11 = 0), 0, IF(OR(Inputs!G15="Y",Inputs!G$24="Y"),PRODUCT(G$11, Prices!$E11),0))*G$10 -> 0 | H29: =IF(OR(Inputs!H$7="Y", H$11 = 0), 0, IF(OR(Inputs!H15="Y",Inputs!H$24="Y"),PRODUCT(H$11, Prices!$E11),0))*H$10 -> 0
C30: PAC/Grouping/Benchmarks | D30: =IF(OR(Inputs!D$7="Y", D$11 = 0), 0, IF(OR(Inputs!D16="Y",Inputs!D$24="Y"),PRODUCT(D$11, Prices!$E12),0))*D$10 -> 0 | E30: =IF(OR(Inputs!E$7="Y", E$11 = 0), 0, IF(OR(Inputs!E16="Y",Inputs!E$24="Y"),PRODUCT(E$11, Prices!$E12),0))*E$10 -> 0 | F30: =IF(OR(Inputs!F$7="Y", F$11 = 0), 0, IF(OR(Inputs!F16="Y",Inputs!F$24="Y"),PRODUCT(F$11, Prices!$E12),0))*F$10 -> 0 | G30: =IF(OR(Inputs!G$7="Y", G$11 = 0), 0, IF(OR(Inputs!G16="Y",Inputs!G$24="Y"),PRODUCT(G$11, Prices!$E12),0))*G$10 -> 0 | H30: =IF(OR(Inputs!H$7="Y", H$11 = 0), 0, IF(OR(Inputs!H16="Y",Inputs!H$24="Y"),PRODUCT(H$11, Prices!$E12),0))*H$10 -> 0
C31: Key Claims Metrics | D31: =IF(OR(Inputs!D$7="Y", D$11 = 0), 0, IF(OR(Inputs!D17="Y",Inputs!D$24="Y"),PRODUCT(D$11, Prices!$E13),0))*D$10 -> 0 | E31: =IF(OR(Inputs!E$7="Y", E$11 = 0), 0, IF(OR(Inputs!E17="Y",Inputs!E$24="Y"),PRODUCT(E$11, Prices!$E13),0))*E$10 -> 0 | F31: =IF(OR(Inputs!F$7="Y", F$11 = 0), 0, IF(OR(Inputs!F17="Y",Inputs!F$24="Y"),PRODUCT(F$11, Prices!$E13),0))*F$10 -> 0 | G31: =IF(OR(Inputs!G$7="Y", G$11 = 0), 0, IF(OR(Inputs!G17="Y",Inputs!G$24="Y"),PRODUCT(G$11, Prices!$E13),0))*G$10 -> 0 | H31: =IF(OR(Inputs!H$7="Y", H$11 = 0), 0, IF(OR(Inputs!H17="Y",Inputs!H$24="Y"),PRODUCT(H$11, Prices!$E13),0))*H$10 -> 0
C32: Waste Calculator | D32: =IF(OR(Inputs!D$7="Y", D$11 = 0), 0, IF(Inputs!D18="Y",PRODUCT(D$11, Prices!$E14),0))*D$10 -> 0 | E32: =IF(OR(Inputs!E$7="Y", E$11 = 0), 0, IF(Inputs!E18="Y",PRODUCT(E$11, Prices!$E14),0))*E$10 -> 0 | F32: =IF(OR(Inputs!F$7="Y", F$11 = 0), 0, IF(Inputs!F18="Y",PRODUCT(F$11, Prices!$E14),0))*F$10 -> 0 | G32: =IF(OR(Inputs!G$7="Y", G$11 = 0), 0, IF(Inputs!G18="Y",PRODUCT(G$11, Prices!$E14),0))*G$10 -> 0 | H32: =IF(OR(Inputs!H$7="Y", H$11 = 0), 0, IF(Inputs!H18="Y",PRODUCT(H$11, Prices!$E14),0))*H$10 -> 0
C33: Medical Conditions | D33: =IF(OR(Inputs!D$7="Y", D$11 = 0), 0, IF(OR(Inputs!D19="Y",Inputs!D$24="Y"),PRODUCT(D$11, Prices!$E15),0))*D$10 -> 0 | E33: =IF(OR(Inputs!E$7="Y", E$11 = 0), 0, IF(OR(Inputs!E19="Y",Inputs!E$24="Y"),PRODUCT(E$11, Prices!$E15),0))*E$10 -> 0 | F33: =IF(OR(Inputs!F$7="Y", F$11 = 0), 0, IF(OR(Inputs!F19="Y",Inputs!F$24="Y"),PRODUCT(F$11, Prices!$E15),0))*F$10 -> 0 | G33: =IF(OR(Inputs!G$7="Y", G$11 = 0), 0, IF(OR(Inputs!G19="Y",Inputs!G$24="Y"),PRODUCT(G$11, Prices!$E15),0))*G$10 -> 0 | H33: =IF(OR(Inputs!H$7="Y", H$11 = 0), 0, IF(OR(Inputs!H19="Y",Inputs!H$24="Y"),PRODUCT(H$11, Prices!$E15),0))*H$10 -> 0
C34: Quality Measures | D34: =IF(OR(Inputs!D$7="Y", D$11 = 0), 0, IF(Inputs!D22="Y",PRODUCT(D$11, Prices!$E16),0))*D$10 -> 0 | E34: =IF(OR(Inputs!E$7="Y", E$11 = 0), 0, IF(Inputs!E22="Y",PRODUCT(E$11, Prices!$E16),0))*E$10 -> 0 | F34: =IF(OR(Inputs!F$7="Y", F$11 = 0), 0, IF(Inputs!F22="Y",PRODUCT(F$11, Prices!$E16),0))*F$10 -> 0 | G34: =IF(OR(Inputs!G$7="Y", G$11 = 0), 0, IF(Inputs!G22="Y",PRODUCT(G$11, Prices!$E16),0))*G$10 -> 0 | H34: =IF(OR(Inputs!H$7="Y", H$11 = 0), 0, IF(Inputs!H22="Y",PRODUCT(H$11, Prices!$E16),0))*H$10 -> 0
C35: PRM Oppourtunity Prospective Scores | D35: =IF(OR(Inputs!D$7="Y", D$11 = 0), 0, IF(OR(Inputs!D20="Y",Inputs!D$25="Y",Inputs!D$26="Y"),PRODUCT(D$11, Prices!$E17),0))*D$10 -> 0 | E35: =IF(OR(Inputs!E$7="Y", E$11 = 0), 0, IF(OR(Inputs!E20="Y",Inputs!E$25="Y",Inputs!E$26="Y"),PRODUCT(E$11, Prices!$E17),0))*E$10 -> 0 | F35: =IF(OR(Inputs!F$7="Y", F$11 = 0), 0, IF(OR(Inputs!F20="Y",Inputs!F$25="Y",Inputs!F$26="Y"),PRODUCT(F$11, Prices!$E17),0))*F$10 -> 0 | G35: =IF(OR(Inputs!G$7="Y", G$11 = 0), 0, IF(OR(Inputs!G20="Y",Inputs!G$25="Y",Inputs!G$26="Y"),PRODUCT(G$11, Prices!$E17),0))*G$10 -> 0 | H35: =IF(OR(Inputs!H$7="Y", H$11 = 0), 0, IF(OR(Inputs!H20="Y",Inputs!H$25="Y",Inputs!H$26="Y"),PRODUCT(H$11, Prices!$E17),0))*H$10 -> 0
C36: PRM Conditions to Consider (Data Only) | D36: =IF(OR(Inputs!D$7="Y", D$11 = 0), 0, IF(OR(Inputs!D21="Y",Inputs!D$25="Y",Inputs!D$26="Y",Inputs!D$29="Y"),PRODUCT(D$11, Prices!$E18),0))*D$10 -> 0 | E36: =IF(OR(Inputs!E$7="Y", E$11 = 0), 0, IF(OR(Inputs!E21="Y",Inputs!E$25="Y",Inputs!E$26="Y",Inputs!E$29="Y"),PRODUCT(E$11, Prices!$E18),0))*E$10 -> 0 | F36: =IF(OR(Inputs!F$7="Y", F$11 = 0), 0, IF(OR(Inputs!F21="Y",Inputs!F$25="Y",Inputs!F$26="Y",Inputs!F$29="Y"),PRODUCT(F$11, Prices!$E18),0))*F$10 -> 0 | G36: =IF(OR(Inputs!G$7="Y", G$11 = 0), 0, IF(OR(Inputs!G21="Y",Inputs!G$25="Y",Inputs!G$26="Y",Inputs!G$29="Y"),PRODUCT(G$11, Prices!$E18),0))*G$10 -> 0 | H36: =IF(OR(Inputs!H$7="Y", H$11 = 0), 0, IF(OR(Inputs!H21="Y",Inputs!H$25="Y",Inputs!H$26="Y",Inputs!H$29="Y"),PRODUCT(H$11, Prices!$E18),0))*H$10 -> 0
C37: PRM Medicare ACO Assignment (CCLF Only) | D37: 0 | E37: 0 | F37: 0 | G37: 0 | H37: 0
B39: Annual Base Data Fees (Actual, with knockouts):
C40: Base Processing Fee | D40: =IF(Inputs!D7="Y", Prices!$C$6, IF(Inputs!D7="N", Prices!$D$6, 0)) -> 15000 | E40: =IF(Inputs!E7="Y", Prices!$C$6, IF(Inputs!E7="N", Prices!$D$6, 0)) -> 0 | F40: =IF(Inputs!F7="Y", Prices!$C$6, IF(Inputs!F7="N", Prices!$D$6, 0)) -> 0 | G40: =IF(Inputs!G7="Y", Prices!$C$6, IF(Inputs!G7="N", Prices!$D$6, 0)) -> 0 | H40: =IF(Inputs!H7="Y", Prices!$C$6, IF(Inputs!H7="N", Prices!$D$6, 0)) -> 0
C41: HCC Risk Scores | D41: =IF(AND(Inputs!D14="Y",Inputs!D$24="N"),Prices!$C10,0) -> 0 | E41: =IF(AND(Inputs!E14="Y",Inputs!E$24="N"),Prices!$C10,0) -> 0 | F41: =IF(AND(Inputs!F14="Y",Inputs!F$24="N"),Prices!$C10,0) -> 0 | G41: =IF(AND(Inputs!G14="Y",Inputs!G$24="N"),Prices!$C10,0) -> 0 | H41: =IF(AND(Inputs!H14="Y",Inputs!H$24="N"),Prices!$C10,0) -> 0
C42: HCG Benchmarks | D42: =IF(AND(Inputs!D15="Y",Inputs!D$24="N"),Prices!$C11,0) -> 0 | E42: =IF(AND(Inputs!E15="Y",Inputs!E$24="N"),Prices!$C11,0) -> 0 | F42: =IF(AND(Inputs!F15="Y",Inputs!F$24="N"),Prices!$C11,0) -> 0 | G42: =IF(AND(Inputs!G15="Y",Inputs!G$24="N"),Prices!$C11,0) -> 0 | H42: =IF(AND(Inputs!H15="Y",Inputs!H$24="N"),Prices!$C11,0) -> 0
C43: PAC/Grouping/Benchmarks | D43: =IF(AND(Inputs!D16="Y",Inputs!D$24="N"),Prices!$C12,0) -> 0 | E43: =IF(AND(Inputs!E16="Y",Inputs!E$24="N"),Prices!$C12,0) -> 0 | F43: =IF(AND(Inputs!F16="Y",Inputs!F$24="N"),Prices!$C12,0) -> 0 | G43: =IF(AND(Inputs!G16="Y",Inputs!G$24="N"),Prices!$C12,0) -> 0 | H43: =IF(AND(Inputs!H16="Y",Inputs!H$24="N"),Prices!$C12,0) -> 0
C44: Key Claims Metrics | D44: =IF(AND(Inputs!D17="Y",Inputs!D$24="N"),Prices!$C13,0) -> 0 | E44: =IF(AND(Inputs!E17="Y",Inputs!E$24="N"),Prices!$C13,0) -> 0 | F44: =IF(AND(Inputs!F17="Y",Inputs!F$24="N"),Prices!$C13,0) -> 0 | G44: =IF(AND(Inputs!G17="Y",Inputs!G$24="N"),Prices!$C13,0) -> 0 | H44: =IF(AND(Inputs!H17="Y",Inputs!H$24="N"),Prices!$C13,0) -> 0
C45: Waste Calculator | D45: =IF(AND(Inputs!D18="Y",Inputs!D$24="N"),Prices!$C14,0) -> 0 | E45: =IF(AND(Inputs!E18="Y",Inputs!E$24="N"),Prices!$C14,0) -> 0 | F45: =IF(AND(Inputs!F18="Y",Inputs!F$24="N"),Prices!$C14,0) -> 0 | G45: =IF(AND(Inputs!G18="Y",Inputs!G$24="N"),Prices!$C14,0) -> 0 | H45: =IF(AND(Inputs!H18="Y",Inputs!H$24="N"),Prices!$C14,0) -> 0
C46: Medical Conditions | D46: =IF(AND(Inputs!D19="Y",Inputs!D$24="N"),Prices!$C15,0) -> 0 | E46: =IF(AND(Inputs!E19="Y",Inputs!E$24="N"),Prices!$C15,0) -> 0 | F46: =IF(AND(Inputs!F19="Y",Inputs!F$24="N"),Prices!$C15,0) -> 0 | G46: =IF(AND(Inputs!G19="Y",Inputs!G$24="N"),Prices!$C15,0) -> 0 | H46: =IF(AND(Inputs!H19="Y",Inputs!H$24="N"),Prices!$C15,0) -> 0
C47: Quality Measures | D47: =IF(Inputs!D22="Y",Prices!$C16,0) -> 0 | E47: =IF(Inputs!E22="Y",Prices!$C16,0) -> 0 | F47: =IF(Inputs!F22="Y",Prices!$C16,0) -> 0 | G47: =IF(Inputs!G22="Y",Prices!$C16,0) -> 0 | H47: =IF(Inputs!H22="Y",Prices!$C16,0) -> 0
C48: PRM Oppourtunity Prospective Scores | D48: =IF(AND(Inputs!D20="Y",Inputs!D$25="N",Inputs!D$26="N"),Prices!$C17,0) -> 0 | E48: =IF(AND(Inputs!E20="Y",Inputs!E$25="N",Inputs!E$26="N"),Prices!$C17,0) -> 0 | F48: =IF(AND(Inputs!F20="Y",Inputs!F$25="N",Inputs!F$26="N"),Prices!$C17,0) -> 0 | G48: =IF(AND(Inputs!G20="Y",Inputs!G$25="N",Inputs!G$26="N"),Prices!$C17,0) -> 0 | H48: =IF(AND(Inputs!H20="Y",Inputs!H$25="N",Inputs!H$26="N"),Prices!$C17,0) -> 0
C49: PRM Conditions to Consider (Data Only) | D49: =IF(AND(Inputs!D21="Y",Inputs!D$25="N",Inputs!D$26="N",Inputs!D$29="N"),Prices!$C18,0) -> 0 | E49: =IF(AND(Inputs!E21="Y",Inputs!E$25="N",Inputs!E$26="N",Inputs!E$29="N"),Prices!$C18,0) -> 0 | F49: =IF(AND(Inputs!F21="Y",Inputs!F$25="N",Inputs!F$26="N",Inputs!F$29="N"),Prices!$C18,0) -> 0 | G49: =IF(AND(Inputs!G21="Y",Inputs!G$25="N",Inputs!G$26="N",Inputs!G$29="N"),Prices!$C18,0) -> 0 | H49: =IF(AND(Inputs!H21="Y",Inputs!H$25="N",Inputs!H$26="N",Inputs!H$29="N"),Prices!$C18,0) -> 0
C50: PRM Medicare ACO Assignment (CCLF Only) | D50: =IF(Inputs!D$7="N",0,IF(AND(Inputs!D22="Y",Inputs!D$25="N",Inputs!D$26="N"),Prices!$C19,0)) -> 0 | E50: =IF(Inputs!E$7="N",0,IF(AND(Inputs!E22="Y",Inputs!E$25="N",Inputs!E$26="N"),Prices!$C19,0)) -> 0 | F50: =IF(Inputs!F$7="N",0,IF(AND(Inputs!F22="Y",Inputs!F$25="N",Inputs!F$26="N"),Prices!$C19,0)) -> 0 | G50: =IF(Inputs!G$7="N",0,IF(AND(Inputs!G22="Y",Inputs!G$25="N",Inputs!G$26="N"),Prices!$C19,0)) -> 0 | H50: =IF(Inputs!H$7="N",0,IF(AND(Inputs!H22="Y",Inputs!H$25="N",Inputs!H$26="N"),Prices!$C19,0)) -> 0
B52: Annual PMPM Add-On Data Fees (Actual, with knockouts):
C53: Base Processing Fee | D53: =IF(Inputs!D$7="Y", 0, IF(D$11 = "", "", PRODUCT(D$11, Prices!$E$6)*D$10)) -> 0 | E53: =IF(Inputs!E$7="Y", 0, IF(E$11 = "", "", PRODUCT(E$11, Prices!$E$6)*E$10)) -> 0 | F53: =IF(Inputs!F$7="Y", 0, IF(F$11 = "", "", PRODUCT(F$11, Prices!$E$6)*F$10)) -> 0 | G53: =IF(Inputs!G$7="Y", 0, IF(G$11 = "", "", PRODUCT(G$11, Prices!$E$6)*G$10)) -> 0 | H53: =IF(Inputs!H$7="Y", 0, IF(H$11 = "", "", PRODUCT(H$11, Prices!$E$6)*H$10)) -> 0
C54: HCC Risk Scores | D54: =IF(OR(Inputs!D$7="Y", D$11 = 0), 0, IF(AND(Inputs!D14="Y",Inputs!D$24="N"),PRODUCT(D$11, Prices!$E10)*D$10,0)) -> 0 | E54: =IF(OR(Inputs!E$7="Y", E$11 = 0), 0, IF(AND(Inputs!E14="Y",Inputs!E$24="N"),PRODUCT(E$11, Prices!$E10)*E$10,0)) -> 0 | F54: =IF(OR(Inputs!F$7="Y", F$11 = 0), 0, IF(AND(Inputs!F14="Y",Inputs!F$24="N"),PRODUCT(F$11, Prices!$E10)*F$10,0)) -> 0 | G54: =IF(OR(Inputs!G$7="Y", G$11 = 0), 0, IF(AND(Inputs!G14="Y",Inputs!G$24="N"),PRODUCT(G$11, Prices!$E10)*G$10,0)) -> 0 | H54: =IF(OR(Inputs!H$7="Y", H$11 = 0), 0, IF(AND(Inputs!H14="Y",Inputs!H$24="N"),PRODUCT(H$11, Prices!$E10)*H$10,0)) -> 0
C55: HCG Benchmarks | D55: =IF(OR(Inputs!D$7="Y", D$11 = 0), 0, IF(AND(Inputs!D15="Y",Inputs!D$24="N"),PRODUCT(D$11, Prices!$E11)*D$10,0)) -> 0 | E55: =IF(OR(Inputs!E$7="Y", E$11 = 0), 0, IF(AND(Inputs!E15="Y",Inputs!E$24="N"),PRODUCT(E$11, Prices!$E11)*E$10,0)) -> 0 | F55: =IF(OR(Inputs!F$7="Y", F$11 = 0), 0, IF(AND(Inputs!F15="Y",Inputs!F$24="N"),PRODUCT(F$11, Prices!$E11)*F$10,0)) -> 0 | G55: =IF(OR(Inputs!G$7="Y", G$11 = 0), 0, IF(AND(Inputs!G15="Y",Inputs!G$24="N"),PRODUCT(G$11, Prices!$E11)*G$10,0)) -> 0 | H55: =IF(OR(Inputs!H$7="Y", H$11 = 0), 0, IF(AND(Inputs!H15="Y",Inputs!H$24="N"),PRODUCT(H$11, Prices!$E11)*H$10,0)) -> 0
C56: PAC/Grouping/Benchmarks | D56: =IF(OR(Inputs!D$7="Y", D$11 = 0), 0, IF(AND(Inputs!D16="Y",Inputs!D$24="N"),PRODUCT(D$11, Prices!$E12)*D$10,0)) -> 0 | E56: =IF(OR(Inputs!E$7="Y", E$11 = 0), 0, IF(AND(Inputs!E16="Y",Inputs!E$24="N"),PRODUCT(E$11, Prices!$E12)*E$10,0)) -> 0 | F56: =IF(OR(Inputs!F$7="Y", F$11 = 0), 0, IF(AND(Inputs!F16="Y",Inputs!F$24="N"),PRODUCT(F$11, Prices!$E12)*F$10,0)) -> 0 | G56: =IF(OR(Inputs!G$7="Y", G$11 = 0), 0, IF(AND(Inputs!G16="Y",Inputs!G$24="N"),PRODUCT(G$11, Prices!$E12)*G$10,0)) -> 0 | H56: =IF(OR(Inputs!H$7="Y", H$11 = 0), 0, IF(AND(Inputs!H16="Y",Inputs!H$24="N"),PRODUCT(H$11, Prices!$E12)*H$10,0)) -> 0
C57: Key Claims Metrics | D57: =IF(OR(Inputs!D$7="Y", D$11 = 0), 0, IF(AND(Inputs!D17="Y",Inputs!D$24="N"),PRODUCT(D$11, Prices!$E13)*D$10,0)) -> 0 | E57: =IF(OR(Inputs!E$7="Y", E$11 = 0), 0, IF(AND(Inputs!E17="Y",Inputs!E$24="N"),PRODUCT(E$11, Prices!$E13)*E$10,0)) -> 0 | F57: =IF(OR(Inputs!F$7="Y", F$11 = 0), 0, IF(AND(Inputs!F17="Y",Inputs!F$24="N"),PRODUCT(F$11, Prices!$E13)*F$10,0)) -> 0 | G57: =IF(OR(Inputs!G$7="Y", G$11 = 0), 0, IF(AND(Inputs!G17="Y",Inputs!G$24="N"),PRODUCT(G$11, Prices!$E13)*G$10,0)) -> 0 | H57: =IF(OR(Inputs!H$7="Y", H$11 = 0), 0, IF(AND(Inputs!H17="Y",Inputs!H$24="N"),PRODUCT(H$11, Prices!$E13)*H$10,0)) -> 0
C58: Waste Calculator | D58: =IF(OR(Inputs!D$7="Y", D$11 = 0), 0, IF(AND(Inputs!D18="Y",Inputs!D$24="N"),PRODUCT(D$11, Prices!$E14)*D$10,0)) -> 0 | E58: =IF(OR(Inputs!E$7="Y", E$11 = 0), 0, IF(AND(Inputs!E18="Y",Inputs!E$24="N"),PRODUCT(E$11, Prices!$E14)*E$10,0)) -> 0 | F58: =IF(OR(Inputs!F$7="Y", F$11 = 0), 0, IF(AND(Inputs!F18="Y",Inputs!F$24="N"),PRODUCT(F$11, Prices!$E14)*F$10,0)) -> 0 | G58: =IF(OR(Inputs!G$7="Y", G$11 = 0), 0, IF(AND(Inputs!G18="Y",Inputs!G$24="N"),PRODUCT(G$11, Prices!$E14)*G$10,0)) -> 0 | H58: =IF(OR(Inputs!H$7="Y", H$11 = 0), 0, IF(AND(Inputs!H18="Y",Inputs!H$24="N"),PRODUCT(H$11, Prices!$E14)*H$10,0)) -> 0
C59: Medical Conditions | D59: =IF(OR(Inputs!D$7="Y", D$11 = 0), 0, IF(AND(Inputs!D19="Y",Inputs!D$24="N"),PRODUCT(D$11, Prices!$E15)*D$10,0)) -> 0 | E59: =IF(OR(Inputs!E$7="Y", E$11 = 0), 0, IF(AND(Inputs!E19="Y",Inputs!E$24="N"),PRODUCT(E$11, Prices!$E15)*E$10,0)) -> 0 | F59: =IF(OR(Inputs!F$7="Y", F$11 = 0), 0, IF(AND(Inputs!F19="Y",Inputs!F$24="N"),PRODUCT(F$11, Prices!$E15)*F$10,0)) -> 0 | G59: =IF(OR(Inputs!G$7="Y", G$11 = 0), 0, IF(AND(Inputs!G19="Y",Inputs!G$24="N"),PRODUCT(G$11, Prices!$E15)*G$10,0)) -> 0 | H59: =IF(OR(Inputs!H$7="Y", H$11 = 0), 0, IF(AND(Inputs!H19="Y",Inputs!H$24="N"),PRODUCT(H$11, Prices!$E15)*H$10,0)) -> 0
C60: Quality Measures | D60: =IF(OR(Inputs!D$7="Y", D$11 = 0), 0, IF(Inputs!D22="Y",PRODUCT(D$11, Prices!$E16)*D$10,0)) -> 0 | E60: =IF(OR(Inputs!E$7="Y", E$11 = 0), 0, IF(Inputs!E22="Y",PRODUCT(E$11, Prices!$E16)*E$10,0)) -> 0 | F60: =IF(OR(Inputs!F$7="Y", F$11 = 0), 0, IF(Inputs!F22="Y",PRODUCT(F$11, Prices!$E16)*F$10,0)) -> 0 | G60: =IF(OR(Inputs!G$7="Y", G$11 = 0), 0, IF(Inputs!G22="Y",PRODUCT(G$11, Prices!$E16)*G$10,0)) -> 0 | H60: =IF(OR(Inputs!H$7="Y", H$11 = 0), 0, IF(Inputs!H22="Y",PRODUCT(H$11, Prices!$E16)*H$10,0)) -> 0
C61: PRM Oppourtunity Prospective Scores | D61: =IF(OR(Inputs!D$7="Y", D$11 = 0), 0, IF(AND(Inputs!D20="Y",Inputs!D$25="N",Inputs!D$26="N"),PRODUCT(D$11, Prices!$E17)*D$10,0)) -> 0 | E61: =IF(OR(Inputs!E$7="Y", E$11 = 0), 0, IF(AND(Inputs!E20="Y",Inputs!E$25="N",Inputs!E$26="N"),PRODUCT(E$11, Prices!$E17)*E$10,0)) -> 0 | F61: =IF(OR(Inputs!F$7="Y", F$11 = 0), 0, IF(AND(Inputs!F20="Y",Inputs!F$25="N",Inputs!F$26="N"),PRODUCT(F$11, Prices!$E17)*F$10,0)) -> 0 | G61: =IF(OR(Inputs!G$7="Y", G$11 = 0), 0, IF(AND(Inputs!G20="Y",Inputs!G$25="N",Inputs!G$26="N"),PRODUCT(G$11, Prices!$E17)*G$10,0)) -> 0 | H61: =IF(OR(Inputs!H$7="Y", H$11 = 0), 0, IF(AND(Inputs!H20="Y",Inputs!H$25="N",Inputs!H$26="N"),PRODUCT(H$11, Prices!$E17)*H$10,0)) -> 0
C62: PRM Conditions to Consider (Data Only) | D62: =IF(OR(Inputs!D$7="Y", D$11 = 0), 0, IF(AND(Inputs!D21="Y",Inputs!D$25="N",Inputs!D$26="N",Inputs!D$29="N"),PRODUCT(D$11, Prices!$E18)*D$10,0)) -> 0 | E62: =IF(OR(Inputs!E$7="Y", E$11 = 0), 0, IF(AND(Inputs!E21="Y",Inputs!E$25="N",Inputs!E$26="N",Inputs!E$29="N"),PRODUCT(E$11, Prices!$E18)*E$10,0)) -> 0 | F62: =IF(OR(Inputs!F$7="Y", F$11 = 0), 0, IF(AND(Inputs!F21="Y",Inputs!F$25="N",Inputs!F$26="N",Inputs!F$29="N"),PRODUCT(F$11, Prices!$E18)*F$10,0)) -> 0 | G62: =IF(OR(Inputs!G$7="Y", G$11 = 0), 0, IF(AND(Inputs!G21="Y",Inputs!G$25="N",Inputs!G$26="N",Inputs!G$29="N"),PRODUCT(G$11, Prices!$E18)*G$10,0)) -> 0 | H62: =IF(OR(Inputs!H$7="Y", H$11 = 0), 0, IF(AND(Inputs!H21="Y",Inputs!H$25="N",Inputs!H$26="N",Inputs!H$29="N"),PRODUCT(H$11, Prices!$E18)*H$10,0)) -> 0
C63: PRM Medicare ACO Assignment (CCLF Only) | D63: 0 | E63: 0 | F63: 0 | G63: 0 | H63: 0
B65: Annual Base Product Fees (Full fees)
C66: ACO Insight - Basic | D66: =IF(Inputs!D$24 = "Y", 0, IF(Inputs!D23="Y", Prices!$C21, 0)) -> 0 | E66: =IF(Inputs!E$24 = "Y", 0, IF(Inputs!E23="Y", Prices!$C21, 0)) -> 0 | F66: =IF(Inputs!F$24 = "Y", 0, IF(Inputs!F23="Y", Prices!$C21, 0)) -> 0 | G66: =IF(Inputs!G$24 = "Y", 0, IF(Inputs!G23="Y", Prices!$C21, 0)) -> 0 | H66: =IF(Inputs!H$24 = "Y", 0, IF(Inputs!H23="Y", Prices!$C21, 0)) -> 0
C67: ACO Insight - Enhanced | D67: =IF(Inputs!D24="Y", Prices!$C22, 0) -> 33000 | E67: =IF(Inputs!E24="Y", Prices!$C22, 0) -> 0 | F67: =IF(Inputs!F24="Y", Prices!$C22, 0) -> 0 | G67: =IF(Inputs!G24="Y", Prices!$C22, 0) -> 0 | H67: =IF(Inputs!H24="Y", Prices!$C22, 0) -> 0
C68: PRM Care Coordinator Report | D68: =IF(Inputs!D25="Y", Prices!$C23, 0) -> 0 | E68: =IF(Inputs!E25="Y", Prices!$C23, 0) -> 0 | F68: =IF(Inputs!F25="Y", Prices!$C23, 0) -> 0 | G68: =IF(Inputs!G25="Y", Prices!$C23, 0) -> 0 | H68: =IF(Inputs!H25="Y", Prices!$C23, 0) -> 0
C69: PRM Caregiver's Checklist | D69: =IF(Inputs!D26="Y", Prices!$C24, 0) -> 0 | E69: =IF(Inputs!E26="Y", Prices!$C24, 0) -> 0 | F69: =IF(Inputs!F26="Y", Prices!$C24, 0) -> 0 | G69: =IF(Inputs!G26="Y", Prices!$C24, 0) -> 0 | H69: =IF(Inputs!H26="Y", Prices!$C24, 0) -> 0
C70: PRM Physician Risk and Credibility Adjusted Report | D70: =IF(Inputs!D27="Y", Prices!$C25, 0) -> 0 | E70: =IF(Inputs!E27="Y", Prices!$C25, 0) -> 0 | F70: =IF(Inputs!F27="Y", Prices!$C25, 0) -> 0 | G70: =IF(Inputs!G27="Y", Prices!$C25, 0) -> 0 | H70: =IF(Inputs!H27="Y", Prices!$C25, 0) -> 0
C71: PRM PCP Dashboard | D71: =IF(Inputs!D28="Y", Prices!$C26 * IF(Inputs!D27="Y",1-Prices!$L$21,1), IF(Inputs!D28="Monthly", Prices!$C26 * Prices!$L$30 * IF(Inputs!D27="Y",1-Prices!$L$21,1), 0)) -> 0 | E71: =IF(Inputs!E28="Y", Prices!$C26 * IF(Inputs!E27="Y",1-Prices!$L$21,1), IF(Inputs!E28="Monthly", Prices!$C26 * Prices!$L$30 * IF(Inputs!E27="Y",1-Prices!$L$21,1), 0)) -> 0 | F71: =IF(Inputs!F28="Y", Prices!$C26 * IF(Inputs!F27="Y",1-Prices!$L$21,1), IF(Inputs!F28="Monthly", Prices!$C26 * Prices!$L$30 * IF(Inputs!F27="Y",1-Prices!$L$21,1), 0)) -> 0 | G71: =IF(Inputs!G28="Y", Prices!$C26 * IF(Inputs!G27="Y",1-Prices!$L$21,1), IF(Inputs!G28="Monthly", Prices!$C26 * Prices!$L$30 * IF(Inputs!G27="Y",1-Prices!$L$21,1), 0)) -> 0 | H71: =IF(Inputs!H28="Y", Prices!$C26 * IF(Inputs!H27="Y",1-Prices!$L$21,1), IF(Inputs!H28="Monthly", Prices!$C26 * Prices!$L$30 * IF(Inputs!H27="Y",1-Prices!$L$21,1), 0)) -> 0
C72: PRM Conditions to Consider Dashboards | D72: =IF(Inputs!D29="Y", Prices!$C27, 0) -> 0 | E72: =IF(Inputs!E29="Y", Prices!$C27, 0) -> 0 | F72: =IF(Inputs!F29="Y", Prices!$C27, 0) -> 0 | G72: =IF(Inputs!G29="Y", Prices!$C27, 0) -> 0 | H72: =IF(Inputs!H29="Y", Prices!$C27, 0) -> 0
C73: Patient Flow | D73: =IF(Inputs!D30="Y", Prices!$C28, 0) -> 0 | E73: =IF(Inputs!E30="Y", Prices!$C28, 0) -> 0 | F73: =IF(Inputs!F30="Y", Prices!$C28, 0) -> 0 | G73: =IF(Inputs!G30="Y", Prices!$C28, 0) -> 0 | H73: =IF(Inputs!H30="Y", Prices!$C28, 0) -> 0
C74: Data Mart | D74: =IF(Inputs!D13="Y", Prices!$C29, IF(Inputs!D13="Monthly", Prices!C29 * Prices!$L$30, 0)) -> 9600 | E74: =IF(Inputs!E13="Y", Prices!$C29, IF(Inputs!E13="Monthly", Prices!D29 * Prices!$L$30, 0)) -> 0 | F74: =IF(Inputs!F13="Y", Prices!$C29, IF(Inputs!F13="Monthly", Prices!E29 * Prices!$L$30, 0)) -> 0 | G74: =IF(Inputs!G13="Y", Prices!$C29, IF(Inputs!G13="Monthly", Prices!F29 * Prices!$L$30, 0)) -> 0 | H74: =IF(Inputs!H13="Y", Prices!$C29, IF(Inputs!H13="Monthly", Prices!G29 * Prices!$L$30, 0)) -> 0
B76: Annual PMPY Add-On Product Fees (Full fees) | J76: Noise
C77: ACO Insight - Basic | D77: 0 | E77: 0 | F77: 0 | G77: 0 | H77: 0 | J77: 0.001 | K77: =D66+D77+$J77 -> 0.001 | L77: =E66+E77+$J77 -> 0.001 | M77: =F66+F77+$J77 -> 0.001 | N77: =G66+G77+$J77 -> 0.001 | O77: =H66+H77+$J77 -> 0.001
C78: ACO Insight - Enhanced | D78: =IF(Inputs!D$7="Y", 0, IF(D$11 = "", 0, IF(Inputs!D24 = "Y", D$11*Prices!$E22, 0)))*D$10 -> 0 | E78: =IF(Inputs!E$7="Y", 0, IF(E$11 = "", 0, IF(Inputs!E24 = "Y", E$11*Prices!$E22, 0)))*E$10 -> 0 | F78: =IF(Inputs!F$7="Y", 0, IF(F$11 = "", 0, IF(Inputs!F24 = "Y", F$11*Prices!$E22, 0)))*F$10 -> 0 | G78: =IF(Inputs!G$7="Y", 0, IF(G$11 = "", 0, IF(Inputs!G24 = "Y", G$11*Prices!$E22, 0)))*G$10 -> 0 | H78: =IF(Inputs!H$7="Y", 0, IF(H$11 = "", 0, IF(Inputs!H24 = "Y", H$11*Prices!$E22, 0)))*H$10 -> 0 | J78: =J77+0.0001 -> 0.0011 | K78: =D67+D78+$J78 -> 33000.001 | L78: =E67+E78+$J78 -> 0.0011 | M78: =F67+F78+$J78 -> 0.0011 | N78: =G67+G78+$J78 -> 0.0011 | O78: =H67+H78+$J78 -> 0.0011
C79: PRM Care Coordinator Report | D79: =IF(Inputs!D$7="Y", 0, IF(D$11 = "", 0, IF(Inputs!D25 = "Y", D$11*Prices!$E23, 0)))*D$10 -> 0 | E79: =IF(Inputs!E$7="Y", 0, IF(E$11 = "", 0, IF(Inputs!E25 = "Y", E$11*Prices!$E23, 0)))*E$10 -> 0 | F79: =IF(Inputs!F$7="Y", 0, IF(F$11 = "", 0, IF(Inputs!F25 = "Y", F$11*Prices!$E23, 0)))*F$10 -> 0 | G79: =IF(Inputs!G$7="Y", 0, IF(G$11 = "", 0, IF(Inputs!G25 = "Y", G$11*Prices!$E23, 0)))*G$10 -> 0 | H79: =IF(Inputs!H$7="Y", 0, IF(H$11 = "", 0, IF(Inputs!H25 = "Y", H$11*Prices!$E23, 0)))*H$10 -> 0 | J79: =J78+0.0001 -> 0.0012 | K79: =D68+D79+$J79 -> 0.0012 | L79: =E68+E79+$J79 -> 0.0012 | M79: =F68+F79+$J79 -> 0.0012 | N79: =G68+G79+$J79 -> 0.0012 | O79: =H68+H79+$J79 -> 0.0012
C80: PRM Caregiver's Checklist | D80: =IF(Inputs!D$7="Y", 0, IF(D$11 = "", 0, IF(Inputs!D26 = "Y", D$11*Prices!$E24, 0)))*D$10 -> 0 | E80: =IF(Inputs!E$7="Y", 0, IF(E$11 = "", 0, IF(Inputs!E26 = "Y", E$11*Prices!$E24, 0)))*E$10 -> 0 | F80: =IF(Inputs!F$7="Y", 0, IF(F$11 = "", 0, IF(Inputs!F26 = "Y", F$11*Prices!$E24, 0)))*F$10 -> 0 | G80: =IF(Inputs!G$7="Y", 0, IF(G$11 = "", 0, IF(Inputs!G26 = "Y", G$11*Prices!$E24, 0)))*G$10 -> 0 | H80: =IF(Inputs!H$7="Y", 0, IF(H$11 = "", 0, IF(Inputs!H26 = "Y", H$11*Prices!$E24, 0)))*H$10 -> 0 | J80: =J79+0.0001 -> 0.0013 | K80: =D69+D80+$J80 -> 0.0013 | L80: =E69+E80+$J80 -> 0.0013 | M80: =F69+F80+$J80 -> 0.0013 | N80: =G69+G80+$J80 -> 0.0013 | O80: =H69+H80+$J80 -> 0.0013
C81: PRM Physician Risk and Credibility Adjusted Report | D81: =IF(Inputs!D$7="Y", 0, IF(D$11 = "", 0, IF(Inputs!D27 = "Y", D$11*Prices!$E25, 0)))*D$10 -> 0 | E81: =IF(Inputs!E$7="Y", 0, IF(E$11 = "", 0, IF(Inputs!E27 = "Y", E$11*Prices!$E25, 0)))*E$10 -> 0 | F81: =IF(Inputs!F$7="Y", 0, IF(F$11 = "", 0, IF(Inputs!F27 = "Y", F$11*Prices!$E25, 0)))*F$10 -> 0 | G81: =IF(Inputs!G$7="Y", 0, IF(G$11 = "", 0, IF(Inputs!G27 = "Y", G$11*Prices!$E25, 0)))*G$10 -> 0 | H81: =IF(Inputs!H$7="Y", 0, IF(H$11 = "", 0, IF(Inputs!H27 = "Y", H$11*Prices!$E25, 0)))*H$10 -> 0 | J81: =J80+0.0001 -> 0.0014 | K81: =D70+D81+$J81 -> 0.0014 | L81: =E70+E81+$J81 -> 0.0014 | M81: =F70+F81+$J81 -> 0.0014 | N81: =G70+G81+$J81 -> 0.0014 | O81: =H70+H81+$J81 -> 0.0014
C82: PRM PCP Dashboard | D82: =IF(Inputs!D$7="Y", 0, IF(D$11 = "", 0, IF(Inputs!D28 = "Y", D$11*Prices!$E26 * IF(Inputs!D27="Y",1-Prices!$L$21,1),IF(Inputs!D28="Monthly", D$11*Prices!$E26 * Prices!$L$30 * IF(Inputs!D27="Y",1-Prices!$L$21,1), 0))))*D$10 -> 0 | E82: =IF(Inputs!E$7="Y", 0, IF(E$11 = "", 0, IF(Inputs!E28 = "Y", E$11*Prices!$E26 * IF(Inputs!E27="Y",1-Prices!$L$21,1),IF(Inputs!E28="Monthly", E$11*Prices!$E26 * Prices!$L$30 * IF(Inputs!E27="Y",1-Prices!$L$21,1), 0))))*E$10 -> 0 | F82: =IF(Inputs!F$7="Y", 0, IF(F$11 = "", 0, IF(Inputs!F28 = "Y", F$11*Prices!$E26 * IF(Inputs!F27="Y",1-Prices!$L$21,1),IF(Inputs!F28="Monthly", F$11*Prices!$E26 * Prices!$L$30 * IF(Inputs!F27="Y",1-Prices!$L$21,1), 0))))*F$10 -> 0 | G82: =IF(Inputs!G$7="Y", 0, IF(G$11 = "", 0, IF(Inputs!G28 = "Y", G$11*Prices!$E26 * IF(Inputs!G27="Y",1-Prices!$L$21,1),IF(Inputs!G28="Monthly", G$11*Prices!$E26 * Prices!$L$30 * IF(Inputs!G27="Y",1-Prices!$L$21,1), 0))))*G$10 -> 0 | H82: =IF(Inputs!H$7="Y", 0, IF(H$11 = "", 0, IF(Inputs!H28 = "Y", H$11*Prices!$E26 * IF(Inputs!H27="Y",1-Prices!$L$21,1),IF(Inputs!H28="Monthly", H$11*Prices!$E26 * Prices!$L$30 * IF(Inputs!H27="Y",1-Prices!$L$21,1), 0))))*H$10 -> 0 | J82: =J81+0.0001 -> 0.0015 | K82: =D71+D82+$J82 -> 0.0015 | L82: =E71+E82+$J82 -> 0.0015 | M82: =F71+F82+$J82 -> 0.0015 | N82: =G71+G82+$J82 -> 0.0015 | O82: =H71+H82+$J82 -> 0.0015
C83: PRM Conditions to Consider Dashboards | D83: =IF(Inputs!D$7="Y", 0, IF(D$11 = "", 0, IF(Inputs!D29 = "Y", D$11*Prices!$E27, 0)))*D$10 -> 0 | E83: =IF(Inputs!E$7="Y", 0, IF(E$11 = "", 0, IF(Inputs!E29 = "Y", E$11*Prices!$E27, 0)))*E$10 -> 0 | F83: =IF(Inputs!F$7="Y", 0, IF(F$11 = "", 0, IF(Inputs!F29 = "Y", F$11*Prices!$E27, 0)))*F$10 -> 0 | G83: =IF(Inputs!G$7="Y", 0, IF(G$11 = "", 0, IF(Inputs!G29 = "Y", G$11*Prices!$E27, 0)))*G$10 -> 0 | H83: =IF(Inputs!H$7="Y", 0, IF(H$11 = "", 0, IF(Inputs!H29 = "Y", H$11*Prices!$E27, 0)))*H$10 -> 0 | J83: =J82+0.0001 -> 0.0016 | K83: =D72+D83+$J83 -> 0.0016 | L83: =E72+E83+$J83 -> 0.0016 | M83: =F72+F83+$J83 -> 0.0016 | N83: =G72+G83+$J83 -> 0.0016 | O83: =H72+H83+$J83 -> 0.0016
C84: Patient Flow | D84: =IF(Inputs!D$7="Y", 0, IF(D$11 = "", 0, IF(Inputs!D30 = "Y", D$11*Prices!$E28, 0)))*D$10 -> 0 | E84: =IF(Inputs!E$7="Y", 0, IF(E$11 = "", 0, IF(Inputs!E30 = "Y", E$11*Prices!$E28, 0)))*E$10 -> 0 | F84: =IF(Inputs!F$7="Y", 0, IF(F$11 = "", 0, IF(Inputs!F30 = "Y", F$11*Prices!$E28, 0)))*F$10 -> 0 | G84: =IF(Inputs!G$7="Y", 0, IF(G$11 = "", 0, IF(Inputs!G30 = "Y", G$11*Prices!$E28, 0)))*G$10 -> 0 | H84: =IF(Inputs!H$7="Y", 0, IF(H$11 = "", 0, IF(Inputs!H30 = "Y", H$11*Prices!$E28, 0)))*H$10 -> 0 | J84: =J83+0.0001 -> 0.0017 | K84: =D73+D84+$J84 -> 0.0017 | L84: =E73+E84+$J84 -> 0.0017 | M84: =F73+F84+$J84 -> 0.0017 | N84: =G73+G84+$J84 -> 0.0017 | O84: =H73+H84+$J84 -> 0.0017
C85: Data Mart | D85: =IF(Inputs!D$7="Y", 0, IF(D$11 = "", 0, IF(Inputs!D13 = "Y", D$11*Prices!$E29, IF(Inputs!D13="Monthly", D$11*Prices!$E29*Prices!$L$30,0))))*D$10 -> 0 | E85: =IF(Inputs!E$7="Y", 0, IF(E$11 = "", 0, IF(Inputs!E13 = "Y", E$11*Prices!$E29, IF(Inputs!E13="Monthly", E$11*Prices!$E29*Prices!$L$30,0))))*E$10 -> 0 | F85: =IF(Inputs!F$7="Y", 0, IF(F$11 = "", 0, IF(Inputs!F13 = "Y", F$11*Prices!$E29, IF(Inputs!F13="Monthly", F$11*Prices!$E29*Prices!$L$30,0))))*F$10 -> 0 | G85: =IF(Inputs!G$7="Y", 0, IF(G$11 = "", 0, IF(Inputs!G13 = "Y", G$11*Prices!$E29, IF(Inputs!G13="Monthly", G$11*Prices!$E29*Prices!$L$30,0))))*G$10 -> 0 | H85: =IF(Inputs!H$7="Y", 0, IF(H$11 = "", 0, IF(Inputs!H13 = "Y", H$11*Prices!$E29, IF(Inputs!H13="Monthly", H$11*Prices!$E29*Prices!$L$30,0))))*H$10 -> 0 | J85: =J84+0.0001 -> 0.0018 | K85: =IF(Inputs!$C$4="Yes", 0, D74+D85+$J85) -> 9600.0018 | L85: =IF(Inputs!$C$4="Yes", 0, E74+E85+$J85) -> 0.0018 | M85: =IF(Inputs!$C$4="Yes", 0, F74+F85+$J85) -> 0.0018 | N85: =IF(Inputs!$C$4="Yes", 0, G74+G85+$J85) -> 0.0018 | O85: =IF(Inputs!$C$4="Yes", 0, H74+H85+$J85) -> 0.0018
B87: Annual Base Product Fees (Marginal over data fees)
C88: ACO Insight - Basic | D88: =D66 -> 0 | E88: =E66 -> 0 | F88: =F66 -> 0 | G88: =G66 -> 0 | H88: =H66 -> 0 | K88: =IF(COUNTIF(K$77:K$85,"")>2,"",IFERROR(RANK(K77,K$77:K$85),8)) -> 9 | L88: =IF(COUNTIF(L$77:L$85,"")>2,"",IFERROR(RANK(L77,L$77:L$85),8)) -> 9 | M88: =IF(COUNTIF(M$77:M$85,"")>2,"",IFERROR(RANK(M77,M$77:M$85),8)) -> 9 | N88: =IF(COUNTIF(N$77:N$85,"")>2,"",IFERROR(RANK(N77,N$77:N$85),8)) -> 9 | O88: =IF(COUNTIF(O$77:O$85,"")>2,"",IFERROR(RANK(O77,O$77:O$85),8)) -> 9
C89: ACO Insight - Enhanced | D89: =IF(D67=0,0,D67-SUM(D15:D20)) -> 14000 | E89: =IF(E67=0,0,E67-SUM(E15:E20)) -> 0 | F89: =IF(F67=0,0,F67-SUM(F15:F20)) -> 0 | G89: =IF(G67=0,0,G67-SUM(G15:G20)) -> 0 | H89: =IF(H67=0,0,H67-SUM(H15:H20)) -> 0 | K89: =IF(COUNTIF(K$77:K$85,"")>2,"",IFERROR(RANK(K78,K$77:K$85),8)) -> 1 | L89: =IF(COUNTIF(L$77:L$85,"")>2,"",IFERROR(RANK(L78,L$77:L$85),8)) -> 8 | M89: =IF(COUNTIF(M$77:M$85,"")>2,"",IFERROR(RANK(M78,M$77:M$85),8)) -> 8 | N89: =IF(COUNTIF(N$77:N$85,"")>2,"",IFERROR(RANK(N78,N$77:N$85),8)) -> 8 | O89: =IF(COUNTIF(O$77:O$85,"")>2,"",IFERROR(RANK(O78,O$77:O$85),8)) -> 8
C90: PRM Care Coordinator Report | D90: =IF(D68=0,0,D68-SUM(D22:D24)) -> 0 | E90: =IF(E68=0,0,E68-SUM(E22:E24)) -> 0 | F90: =IF(F68=0,0,F68-SUM(F22:F24)) -> 0 | G90: =IF(G68=0,0,G68-SUM(G22:G24)) -> 0 | H90: =IF(H68=0,0,H68-SUM(H22:H24)) -> 0 | K90: =IF(COUNTIF(K$77:K$85,"")>2,"",IFERROR(RANK(K79,K$77:K$85),8)) -> 8 | L90: =IF(COUNTIF(L$77:L$85,"")>2,"",IFERROR(RANK(L79,L$77:L$85),8)) -> 7 | M90: =IF(COUNTIF(M$77:M$85,"")>2,"",IFERROR(RANK(M79,M$77:M$85),8)) -> 7 | N90: =IF(COUNTIF(N$77:N$85,"")>2,"",IFERROR(RANK(N79,N$77:N$85),8)) -> 7 | O90: =IF(COUNTIF(O$77:O$85,"")>2,"",IFERROR(RANK(O79,O$77:O$85),8)) -> 7
C91: PRM Caregiver's Checklist | D91: =IF(D69=0,0,D69-IF(Inputs!D25="Y", 0, SUM(D22:D24))) -> 0 | E91: =IF(E69=0,0,E69-IF(Inputs!E25="Y", 0, SUM(E22:E24))) -> 0 | F91: =IF(F69=0,0,F69-IF(Inputs!F25="Y", 0, SUM(F22:F24))) -> 0 | G91: =IF(G69=0,0,G69-IF(Inputs!G25="Y", 0, SUM(G22:G24))) -> 0 | H91: =IF(H69=0,0,H69-IF(Inputs!H25="Y", 0, SUM(H22:H24))) -> 0 | K91: =IF(COUNTIF(K$77:K$85,"")>2,"",IFERROR(RANK(K80,K$77:K$85),8)) -> 7 | L91: =IF(COUNTIF(L$77:L$85,"")>2,"",IFERROR(RANK(L80,L$77:L$85),8)) -> 6 | M91: =IF(COUNTIF(M$77:M$85,"")>2,"",IFERROR(RANK(M80,M$77:M$85),8)) -> 6 | N91: =IF(COUNTIF(N$77:N$85,"")>2,"",IFERROR(RANK(N80,N$77:N$85),8)) -> 6 | O91: =IF(COUNTIF(O$77:O$85,"")>2,"",IFERROR(RANK(O80,O$77:O$85),8)) -> 6
C92: PRM Physician Risk and Credibility Adjusted Report | D92: =D70 -> 0 | E92: =E70 -> 0 | F92: =F70 -> 0 | G92: =G70 -> 0 | H92: =H70 -> 0 | K92: =IF(COUNTIF(K$77:K$85,"")>2,"",IFERROR(RANK(K81,K$77:K$85),8)) -> 6 | L92: =IF(COUNTIF(L$77:L$85,"")>2,"",IFERROR(RANK(L81,L$77:L$85),8)) -> 5 | M92: =IF(COUNTIF(M$77:M$85,"")>2,"",IFERROR(RANK(M81,M$77:M$85),8)) -> 5 | N92: =IF(COUNTIF(N$77:N$85,"")>2,"",IFERROR(RANK(N81,N$77:N$85),8)) -> 5 | O92: =IF(COUNTIF(O$77:O$85,"")>2,"",IFERROR(RANK(O81,O$77:O$85),8)) -> 5
C93: PRM PCP Dashboard | D93: =D71 -> 0 | E93: =E71 -> 0 | F93: =F71 -> 0 | G93: =G71 -> 0 | H93: =H71 -> 0 | K93: =IF(COUNTIF(K$77:K$85,"")>2,"",IFERROR(RANK(K82,K$77:K$85),8)) -> 5 | L93: =IF(COUNTIF(L$77:L$85,"")>2,"",IFERROR(RANK(L82,L$77:L$85),8)) -> 4 | M93: =IF(COUNTIF(M$77:M$85,"")>2,"",IFERROR(RANK(M82,M$77:M$85),8)) -> 4 | N93: =IF(COUNTIF(N$77:N$85,"")>2,"",IFERROR(RANK(N82,N$77:N$85),8)) -> 4 | O93: =IF(COUNTIF(O$77:O$85,"")>2,"",IFERROR(RANK(O82,O$77:O$85),8)) -> 4
C94: PRM Conditions to Consider Dashboards | D94: =IF(D72=0,0,D72-IF(OR(Inputs!D25="Y",Inputs!D26="Y"), 0, D23)) -> 0 | E94: =IF(E72=0,0,E72-IF(OR(Inputs!E25="Y",Inputs!E26="Y"), 0, E23)) -> 0 | F94: =IF(F72=0,0,F72-IF(OR(Inputs!F25="Y",Inputs!F26="Y"), 0, F23)) -> 0 | G94: =IF(G72=0,0,G72-IF(OR(Inputs!G25="Y",Inputs!G26="Y"), 0, G23)) -> 0 | H94: =IF(H72=0,0,H72-IF(OR(Inputs!H25="Y",Inputs!H26="Y"), 0, H23)) -> 0 | K94: =IF(COUNTIF(K$77:K$85,"")>2,"",IFERROR(RANK(K83,K$77:K$85),8)) -> 4 | L94: =IF(COUNTIF(L$77:L$85,"")>2,"",IFERROR(RANK(L83,L$77:L$85),8)) -> 3 | M94: =IF(COUNTIF(M$77:M$85,"")>2,"",IFERROR(RANK(M83,M$77:M$85),8)) -> 3 | N94: =IF(COUNTIF(N$77:N$85,"")>2,"",IFERROR(RANK(N83,N$77:N$85),8)) -> 3 | O94: =IF(COUNTIF(O$77:O$85,"")>2,"",IFERROR(RANK(O83,O$77:O$85),8)) -> 3
C95: Patient Flow | D95: =D73 -> 0 | E95: =E73 -> 0 | F95: =F73 -> 0 | G95: =G73 -> 0 | H95: =H73 -> 0 | K95: =IF(COUNTIF(K$77:K$85,"")>2,"",IFERROR(RANK(K84,K$77:K$85),8)) -> 3 | L95: =IF(COUNTIF(L$77:L$85,"")>2,"",IFERROR(RANK(L84,L$77:L$85),8)) -> 2 | M95: =IF(COUNTIF(M$77:M$85,"")>2,"",IFERROR(RANK(M84,M$77:M$85),8)) -> 2 | N95: =IF(COUNTIF(N$77:N$85,"")>2,"",IFERROR(RANK(N84,N$77:N$85),8)) -> 2 | O95: =IF(COUNTIF(O$77:O$85,"")>2,"",IFERROR(RANK(O84,O$77:O$85),8)) -> 2
C96: Data Mart | D96: =D74 -> 9600 | E96: =E74 -> 0 | F96: =F74 -> 0 | G96: =G74 -> 0 | H96: =H74 -> 0 | K96: =IF(COUNTIF(K$77:K$85,"")>2,"",IFERROR(RANK(K85,K$77:K$85),8)) -> 2 | L96: =IF(COUNTIF(L$77:L$85,"")>2,"",IFERROR(RANK(L85,L$77:L$85),8)) -> 1 | M96: =IF(COUNTIF(M$77:M$85,"")>2,"",IFERROR(RANK(M85,M$77:M$85),8)) -> 1 | N96: =IF(COUNTIF(N$77:N$85,"")>2,"",IFERROR(RANK(N85,N$77:N$85),8)) -> 1 | O96: =IF(COUNTIF(O$77:O$85,"")>2,"",IFERROR(RANK(O85,O$77:O$85),8)) -> 1
B98: Annual PMPY Add-On Product Fees (Marginal over data fees)
C99: ACO Insight - Basic | D99: 0 | E99: 0 | F99: 0 | G99: 0 | H99: 0
C100: ACO Insight - Enhanced | D100: =IF(D78=0,0,D78-SUM(D28:D33)) -> 0 | E100: =IF(E78=0,0,E78-SUM(E28:E33)) -> 0 | F100: =IF(F78=0,0,F78-SUM(F28:F33)) -> 0 | G100: =IF(G78=0,0,G78-SUM(G28:G33)) -> 0 | H100: =IF(H78=0,0,H78-SUM(H28:H33)) -> 0
C101: PRM Care Coordinator Report | D101: =IF(D79=0,0,D79-SUM(D35:D36)) -> 0 | E101: =IF(E79=0,0,E79-SUM(E35:E36)) -> 0 | F101: =IF(F79=0,0,F79-SUM(F35:F36)) -> 0 | G101: =IF(G79=0,0,G79-SUM(G35:G36)) -> 0 | H101: =IF(H79=0,0,H79-SUM(H35:H36)) -> 0
C102: PRM Caregiver's Checklist | D102: =IF(D80=0,0,D80-IF(Inputs!D25="Y", 0,SUM(D35:D36))) -> 0 | E102: =IF(E80=0,0,E80-IF(Inputs!E25="Y", 0,SUM(E35:E36))) -> 0 | F102: =IF(F80=0,0,F80-IF(Inputs!F25="Y", 0,SUM(F35:F36))) -> 0 | G102: =IF(G80=0,0,G80-IF(Inputs!G25="Y", 0,SUM(G35:G36))) -> 0 | H102: =IF(H80=0,0,H80-IF(Inputs!H25="Y", 0,SUM(H35:H36))) -> 0
C103: PRM Physician Risk and Credibility Adjusted Report | D103: =D81 -> 0 | E103: =E81 -> 0 | F103: =F81 -> 0 | G103: =G81 -> 0 | H103: =H81 -> 0
C104: PRM PCP Dashboard | D104: =D82 -> 0 | E104: =E82 -> 0 | F104: =F82 -> 0 | G104: =G82 -> 0 | H104: =H82 -> 0
C105: PRM Conditions to Consider Dashboards | D105: =IF(D83=0,0,D83-IF(OR(Inputs!D25="Y",Inputs!D26="Y"), 0, D36)) -> 0 | E105: =IF(E83=0,0,E83-IF(OR(Inputs!E25="Y",Inputs!E26="Y"), 0, E36)) -> 0 | F105: =IF(F83=0,0,F83-IF(OR(Inputs!F25="Y",Inputs!F26="Y"), 0, F36)) -> 0 | G105: =IF(G83=0,0,G83-IF(OR(Inputs!G25="Y",Inputs!G26="Y"), 0, G36)) -> 0 | H105: =IF(H83=0,0,H83-IF(OR(Inputs!H25="Y",Inputs!H26="Y"), 0, H36)) -> 0
C106: Patient Flow | D106: =D84 -> 0 | E106: =E84 -> 0 | F106: =F84 -> 0 | G106: =G84 -> 0 | H106: =H84 -> 0
C107: Data Mart | D107: =D85 -> 0 | E107: =E85 -> 0 | F107: =F85 -> 0 | G107: =G85 -> 0 | H107: =H85 -> 0
B109: Multi-Product Discount
A110: 2 | C110: 2nd Most Expensive Product | D110: =_xlfn.IFNA(SUM(INDEX(D$66:D$74, MATCH($A110, K$88:K$96, 0)), INDEX(D$77:D$85, MATCH($A110, K$88:K$96, 0)))*Prices!$L$5*-1, 0) -> -2880 | E110: =_xlfn.IFNA(SUM(INDEX(E$66:E$74, MATCH($A110, L$88:L$96, 0)), INDEX(E$77:E$85, MATCH($A110, L$88:L$96, 0)))*Prices!$L$5*-1, 0) -> 0 | F110: =_xlfn.IFNA(SUM(INDEX(F$66:F$74, MATCH($A110, M$88:M$96, 0)), INDEX(F$77:F$85, MATCH($A110, M$88:M$96, 0)))*Prices!$L$5*-1, 0) -> 0 | G110: =_xlfn.IFNA(SUM(INDEX(G$66:G$74, MATCH($A110, N$88:N$96, 0)), INDEX(G$77:G$85, MATCH($A110, N$88:N$96, 0)))*Prices!$L$5*-1, 0) -> 0 | H110: =_xlfn.IFNA(SUM(INDEX(H$66:H$74, MATCH($A110, O$88:O$96, 0)), INDEX(H$77:H$85, MATCH($A110, O$88:O$96, 0)))*Prices!$L$5*-1, 0) -> 0
...

Sheet Prices
C2: CCLF | D2: Non-CCLF
B3: Implementation Fees (Per Datafeed) | C3: 5000 | D3: 20000 | K3: Multi-Product Discounts
B4: Implementation Add-On (non-CMS Files) | C4: 5000 | D4: 0 | E4: PMPY Add-Ons | F4: 0.6 | G4: 0.24 | H4: 0.2 | K4: Most Expensive Product | L4: 0
E5: 25k-50k | F5: 50k-100k | G5: 100k-250k | H5: 250k+ | K5: 2nd Most Expensive Product | L5: 0.3
B6: Base Processing Fees | C6: =$L$28*15000 -> 15000 | D6: =IF(Inputs!$C$3="Monthly",33000,30000) -> 30000 | E6: =ROUND(IF(Inputs!$C$3="Monthly",0.4,0.27), 2) -> 0.27 | F6: =ROUND($E6*F$4, 2) -> 0.16 | G6: =ROUND($E6*G$4, 2) -> 0.06 | H6: =MAX(ROUND($E6*H$4, 2) + IF(ROUND($E6*H$4, 2) = G6, -0.01, 0), 0.01) -> 0.05 | K6: 3rd Most Expensive Product | L6: 0.45
K8: Multi-Population Discounts
C9: Base | K9: Most Expensive Population | L9: 0
B10: HCC Risk Scores | C10: =$L$28*1000 -> 1000 | E10: =ROUND($L$28*0.04, 2) -> 0.04 | F10: =ROUND($E10*F$4, 2) -> 0.02 | G10: =ROUND($E10*G$4, 2) -> 0.01 | H10: =MAX(ROUND($E10*H$4, 2) + IF(ROUND($E10*H$4, 2) = G10, -0.01, 0), 0.01) -> 0.01 | K10: 2nd Most Expensive Population | L10: 0.45
B11: HCG Benchmarks | C11: =$L$28*4000 -> 4000 | E11: =ROUND(IF(Inputs!$C$3="Monthly",0.07,0.05), 2) -> 0.05 | F11: =ROUND($E11*F$4, 2) -> 0.03 | G11: =ROUND($E11*G$4, 2) -> 0.01 | H11: =MAX(ROUND($E11*H$4, 2) + IF(ROUND($E11*H$4, 2) = G11, -0.01, 0), 0.01) -> 0.01 | K11: 3rd Most Expensive Population | L11: 0.5
B12: PAC/Grouping/Benchmarks | C12: =$L$28*2000 -> 2000 | E12: =ROUND($L$28*0.04, 2) -> 0.04 | F12: =ROUND($E12*F$4, 2) -> 0.02 | G12: =ROUND($E12*G$4, 2) -> 0.01 | H12: =MAX(ROUND($E12*H$4, 2) + IF(ROUND($E12*H$4, 2) = G12, -0.01, 0), 0.01) -> 0.01
B13: Key Claims Metrics | C13: =$L$28*2000 -> 2000 | E13: =ROUND($L$28*0.04, 2) -> 0.04 | F13: =ROUND($E13*F$4, 2) -> 0.02 | G13: =ROUND($E13*G$4, 2) -> 0.01 | H13: =MAX(ROUND($E13*H$4, 2) + IF(ROUND($E13*H$4, 2) = G13, -0.01, 0), 0.01) -> 0.01
B14: Waste Calculator | C14: =$L$28*6000 -> 6000 | E14: =ROUND(IF(Inputs!$C$3="Monthly",0.07,0.05), 2) -> 0.05 | F14: =ROUND($E14*F$4, 2) -> 0.03 | G14: =ROUND($E14*G$4, 2) -> 0.01 | H14: =MAX(ROUND($E14*H$4, 2) + IF(ROUND($E14*H$4, 2) = G14, -0.01, 0), 0.01) -> 0.01 | K14: Annual Increase | L14: 0.0125
B15: Medical Conditions | C15: =$L$28*4000 -> 4000 | E15: =ROUND(IF(Inputs!$C$3="Monthly",0.07,0.05), 2) -> 0.05 | F15: =ROUND($E15*F$4, 2) -> 0.03 | G15: =ROUND($E15*G$4, 2) -> 0.01 | H15: =MAX(ROUND($E15*H$4, 2) + IF(ROUND($E15*H$4, 2) = G15, -0.01, 0), 0.01) -> 0.01 | K15: First Annual Increase | L15: 43466
B16: Quality Measures | C16: =$L$28*3500 -> 3500 | E16: =ROUND(IF(Inputs!$C$3="Monthly",0.07,0.05), 2) -> 0.05 | F16: =ROUND($E16*F$4, 2) -> 0.03 | G16: =ROUND($E16*G$4, 2) -> 0.01 | H16: =MAX(ROUND($E16*H$4, 2) + IF(ROUND($E16*H$4, 2) = G16, -0.01, 0), 0.01) -> 0.01
B17: PRM Oppourtunity Prospective Scores | C17: =$L$28*10000 -> 10000 | E17: =ROUND(IF(Inputs!$C$3="Monthly",0.25,0.18), 2) -> 0.18 | F17: =ROUND($E17*F$4, 2) -> 0.11 | G17: =ROUND($E17*G$4, 2) -> 0.04 | H17: =MAX(ROUND($E17*H$4, 2) + IF(ROUND($E17*H$4, 2) = G17, -0.01, 0), 0.01) -> 0.03
B18: PRM Conditions to Consider (Data Only) | C18: =$L$28*10000 -> 10000 | E18: =ROUND(IF(Inputs!$C$3="Monthly",0.25,0.18), 2) -> 0.18 | F18: =ROUND($E18*F$4, 2) -> 0.11 | G18: =ROUND($E18*G$4, 2) -> 0.04 | H18: =MAX(ROUND($E18*H$4, 2) + IF(ROUND($E18*H$4, 2) = G18, -0.01, 0), 0.01) -> 0.03
B19: PRM Medicare ACO Assignment (CCLF Only) | C19: =$L$28*1500 -> 1500 | E19: =ROUND($L$28*0, 2) -> 0 | F19: =ROUND($E19*F$4, 2) -> 0 | G19: =ROUND($E19*G$4, 2) -> 0 | H19: =ROUND($E19*H$4, 2) -> 0 | K19: Existing Collaborative Member Discount | L19: 3525
B21: ACO Insight - Basic | C21: =$L$28*8500 -> 8500 | E21: =ROUND($L$28*0, 2) -> 0 | F21: =ROUND($E21*F$4, 2) -> 0 | G21: =ROUND($E21*G$4, 2) -> 0 | H21: =ROUND($E21*H$4, 2) -> 0 | K21: Extra Discount for PRCA & PCP Dashboard | L21: 0.3
B22: ACO Insight - Enhanced | C22: =$L$28*33000 -> 33000 | E22: =ROUND(IF(Inputs!$C$3="Monthly",0.4,0.28), 2) -> 0.28 | F22: =ROUND($E22*F$4, 2) -> 0.17 | G22: =ROUND($E22*G$4, 2) -> 0.07 | H22: =MAX(ROUND($E22*H$4, 2) + IF(ROUND($E22*H$4, 2) = G22, -0.01, 0), 0.01) -> 0.06
B23: PRM Care Coordinator Report | C23: =$L$28*35000 -> 35000 | E23: =ROUND(IF(Inputs!$C$3="Monthly",0.42,0.29), 2) -> 0.29 | F23: =ROUND($E23*F$4, 2) -> 0.17 | G23: =ROUND($E23*G$4, 2) -> 0.07 | H23: =MAX(ROUND($E23*H$4, 2) + IF(ROUND($E23*H$4, 2) = G23, -0.01, 0), 0.01) -> 0.06
B24: PRM Caregiver's Checklist | C24: =$L$28*35000 -> 35000 | E24: =ROUND(IF(Inputs!$C$3="Monthly",0.42,0.29), 2) -> 0.29 | F24: =ROUND($E24*F$4, 2) -> 0.17 | G24: =ROUND($E24*G$4, 2) -> 0.07 | H24: =MAX(ROUND($E24*H$4, 2) + IF(ROUND($E24*H$4, 2) = G24, -0.01, 0), 0.01) -> 0.06
B25: PRM Physician Risk and Credibility Adjusted Report | C25: =$L$28*28000 -> 28000 | E25: =ROUND(IF(Inputs!$C$3="Monthly",0.25,0.18), 2) -> 0.18 | F25: =ROUND($E25*F$4, 2) -> 0.11 | G25: =ROUND($E25*G$4, 2) -> 0.04 | H25: =MAX(ROUND($E25*H$4, 2) + IF(ROUND($E25*H$4, 2) = G25, -0.01, 0), 0.01) -> 0.03 | K25: Monthly Multiplier | L25: =18000/15000 -> 1.2
B26: PRM PCP Dashboard | C26: =$L$28*33600 -> 33600 | E26: =ROUND($L$28*0.25, 2) -> 0.25 | F26: =ROUND($E26*F$4, 2) -> 0.15 | G26: =ROUND($E26*G$4, 2) -> 0.06 | H26: =MAX(ROUND($E26*H$4, 2) + IF(ROUND($E26*H$4, 2) = G26, -0.01, 0), 0.01) -> 0.05
B27: PRM Conditions to Consider Dashboards | C27: =$L$28*28000 -> 28000 | E27: =ROUND(IF(Inputs!$C$3="Monthly",0.25,0.18), 2) -> 0.18 | F27: =ROUND($E27*F$4, 2) -> 0.11 | G27: =ROUND($E27*G$4, 2) -> 0.04 | H27: =MAX(ROUND($E27*H$4, 2) + IF(ROUND($E27*H$4, 2) = G27, -0.01, 0), 0.01) -> 0.03
B28: Patient Flow | C28: =$L$28*20000 -> 20000 | E28: =ROUND($L$28*0.14, 2) -> 0.14 | F28: =ROUND($E28*F$4, 2) -> 0.08 | G28: =ROUND($E28*G$4, 2) -> 0.03 | H28: =MAX(ROUND($E28*H$4, 2) + IF(ROUND($E28*H$4, 2) = G28, -0.01, 0), 0.01) -> 0.02 | K28: Frequency Multiplier | L28: =IF(Inputs!$C$3="Monthly",Prices!$L$25,1) -> 1
B29: Data Mart | C29: =$L$28*IF(Inputs!$C$4 = "Yes", 6750, 9600) -> 9600 | E29: =ROUND(IF(Inputs!$C$3="Monthly",0.6,0.42), 2) -> 0.42 | F29: =ROUND($E29*F$4, 2) -> 0.25 | G29: =ROUND($E29*G$4, 2) -> 0.1 | H29: =MAX(ROUND($E29*H$4, 2) + IF(ROUND($E29*H$4, 2) = G29, -0.01, 0), 0.01) -> 0.08
K30: Monthly Override Multiplier | L30: =IF(Inputs!$C$3="Quarterly",$L$25,1) -> 1.2

Sheet MARA Prices
A1: Lower Bound | B1: Upper Bound | C1: PMPY | E1: Annual Increase | F1: 0.05 | H1: Population #1 | I1: Population #2 | J1: Population #3 | K1: Population #4 | L1: Population #5
A2: 0 | B2: 49999 | C2: 0.2 | E2: First Increase | F2: 43831 | H2: =IF(Inputs!D$11 > $B2, $A3-$A2, MAX(0, Inputs!D$11-$A2)) -> 50000 | I2: =IF(Inputs!E$11 > $B2, $A3-$A2, MAX(0, Inputs!E$11-$A2)) -> 0 | J2: =IF(Inputs!F$11 > $B2, $A3-$A2, MAX(0, Inputs!F$11-$A2)) -> 0 | K2: =IF(Inputs!G$11 > $B2, $A3-$A2, MAX(0, Inputs!G$11-$A2)) -> 0 | L2: =IF(Inputs!H$11 > $B2, $A3-$A2, MAX(0, Inputs!H$11-$A2)) -> 0
A3: 50000 | B3: 99999 | C3: 0.17 | H3: =IF(Inputs!D$11 > $B3, $A4-$A3, MAX(0, Inputs!D$11-$A3)) -> 0 | I3: =IF(Inputs!E$11 > $B3, $A4-$A3, MAX(0, Inputs!E$11-$A3)) -> 0 | J3: =IF(Inputs!F$11 > $B3, $A4-$A3, MAX(0, Inputs!F$11-$A3)) -> 0 | K3: =IF(Inputs!G$11 > $B3, $A4-$A3, MAX(0, Inputs!G$11-$A3)) -> 0 | L3: =IF(Inputs!H$11 > $B3, $A4-$A3, MAX(0, Inputs!H$11-$A3)) -> 0
A4: 100000 | B4: 299999 | C4: 0.14 | E4: MARA Royalty | F4: 0.8 | H4: =IF(Inputs!D$11 > $B4, $A5-$A4, MAX(0, Inputs!D$11-$A4)) -> 0 | I4: =IF(Inputs!E$11 > $B4, $A5-$A4, MAX(0, Inputs!E$11-$A4)) -> 0 | J4: =IF(Inputs!F$11 > $B4, $A5-$A4, MAX(0, Inputs!F$11-$A4)) -> 0 | K4: =IF(Inputs!G$11 > $B4, $A5-$A4, MAX(0, Inputs!G$11-$A4)) -> 0 | L4: =IF(Inputs!H$11 > $B4, $A5-$A4, MAX(0, Inputs!H$11-$A4)) -> 0
A5: 300000 | B5: 499999 | C5: 0.11 | E5: NY Health | F5: 0.1 | H5: =IF(Inputs!D$11 > $B5, $A6-$A5, MAX(0, Inputs!D$11-$A5)) -> 0 | I5: =IF(Inputs!E$11 > $B5, $A6-$A5, MAX(0, Inputs!E$11-$A5)) -> 0 | J5: =IF(Inputs!F$11 > $B5, $A6-$A5, MAX(0, Inputs!F$11-$A5)) -> 0 | K5: =IF(Inputs!G$11 > $B5, $A6-$A5, MAX(0, Inputs!G$11-$A5)) -> 0 | L5: =IF(Inputs!H$11 > $B5, $A6-$A5, MAX(0, Inputs!H$11-$A5)) -> 0
A6: 500000 | B6: 999999 | C6: 0.07 | E6: PRM | F6: 0.1 | H6: =IF(Inputs!D$11 > $B6, $A7-$A6, MAX(0, Inputs!D$11-$A6)) -> 0 | I6: =IF(Inputs!E$11 > $B6, $A7-$A6, MAX(0, Inputs!E$11-$A6)) -> 0 | J6: =IF(Inputs!F$11 > $B6, $A7-$A6, MAX(0, Inputs!F$11-$A6)) -> 0 | K6: =IF(Inputs!G$11 > $B6, $A7-$A6, MAX(0, Inputs!G$11-$A6)) -> 0 | L6: =IF(Inputs!H$11 > $B6, $A7-$A6, MAX(0, Inputs!H$11-$A6)) -> 0
A7: 1000000 | B7: 1999999 | C7: 0.06 | H7: =IF(Inputs!D$11 > $B7, $A8-$A7, MAX(0, Inputs!D$11-$A7)) -> 0 | I7: =IF(Inputs!E$11 > $B7, $A8-$A7, MAX(0, Inputs!E$11-$A7)) -> 0 | J7: =IF(Inputs!F$11 > $B7, $A8-$A7, MAX(0, Inputs!F$11-$A7)) -> 0 | K7: =IF(Inputs!G$11 > $B7, $A8-$A7, MAX(0, Inputs!G$11-$A7)) -> 0 | L7: =IF(Inputs!H$11 > $B7, $A8-$A7, MAX(0, Inputs!H$11-$A7)) -> 0
A8: 2000000 | B8: 5000000 | C8: 0.04 | H8: =IF(Inputs!D$11 > $B8, $A9-$A8, MAX(0, Inputs!D$11-$A8)) -> 0 | I8: =IF(Inputs!E$11 > $B8, $A9-$A8, MAX(0, Inputs!E$11-$A8)) -> 0 | J8: =IF(Inputs!F$11 > $B8, $A9-$A8, MAX(0, Inputs!F$11-$A8)) -> 0 | K8: =IF(Inputs!G$11 > $B8, $A9-$A8, MAX(0, Inputs!G$11-$A8)) -> 0 | L8: =IF(Inputs!H$11 > $B8, $A9-$A8, MAX(0, Inputs!H$11-$A8)) -> 0
H10: =H2*$C2 -> 10000 | I10: =I2*$C2 -> 0 | J10: =J2*$C2 -> 0 | K10: =K2*$C2 -> 0 | L10: =L2*$C2 -> 0
H11: =H3*$C3 -> 0 | I11: =I3*$C3 -> 0 | J11: =J3*$C3 -> 0 | K11: =K3*$C3 -> 0 | L11: =L3*$C3 -> 0
H12: =H4*$C4 -> 0 | I12: =I4*$C4 -> 0 | J12: =J4*$C4 -> 0 | K12: =K4*$C4 -> 0 | L12: =L4*$C4 -> 0
H13: =H5*$C5 -> 0 | I13: =I5*$C5 -> 0 | J13: =J5*$C5 -> 0 | K13: =K5*$C5 -> 0 | L13: =L5*$C5 -> 0
H14: =H6*$C6 -> 0 | I14: =I6*$C6 -> 0 | J14: =J6*$C6 -> 0 | K14: =K6*$C6 -> 0 | L14: =L6*$C6 -> 0
H15: =H7*$C7 -> 0 | I15: =I7*$C7 -> 0 | J15: =J7*$C7 -> 0 | K15: =K7*$C7 -> 0 | L15: =L7*$C7 -> 0
H16: =H8*$C8 -> 0 | I16: =I8*$C8 -> 0 | J16: =J8*$C8 -> 0 | K16: =K8*$C8 -> 0 | L16: =L8*$C8 -> 0
H19: Population #1 | I19: Population #2 | J19: Population #3 | K19: Population #4 | L19: Population #5
G20: Total | H20: =IF(Inputs!D$10 = "Y", SUM(H10:H16), 0) -> 0 | I20: =IF(Inputs!E$10 = "Y", SUM(I10:I16), 0) -> 0 | J20: =IF(Inputs!F$10 = "Y", SUM(J10:J16), 0) -> 0 | K20: =IF(Inputs!G$10 = "Y", SUM(K10:K16), 0) -> 0 | L20: =IF(Inputs!H$10 = "Y", SUM(L10:L16), 0) -> 0
G21: Monthly | H21: =H20/12 -> 0 | I21: =I20/12 -> 0 | J21: =J20/12 -> 0 | K21: =K20/12 -> 0 | L21: =L20/12 -> 0
