Workbook
Name Annual_Membership: '[1]MI License Price'!$A$4
Name Delivery_Selection: 'MI Price Sheet'!#REF!
Name Original: Lists!$H$1:$H$4

Sheet Contract Summary
A1: CONTRACT FACE SHEET
A2: FACE SHEET COMPLETED BY: | B2: McKinley | C2: FACE SHEET APPROVED BY: | D2: Zoelzer
A3: Client Legal Name | B3: Payformance Solutions, Inc. (They're a subsidiary of Altarum) | C3: Client Code | D3: 0273PFS01; 0009PFS01
A4: Client Abbreviated Name | B4: Payformance | C4: Salesperson | D4: McKinley
A5: Type of contract | B5: New | C5: Contract Term (months) | D5: 120 days after access to data
A6: Date contract was fully executed by both parties | B6: 43165 | C6: Current Contract/ Amendment eff date | D6: 43165
A7: Original Contract eff date | B7: 43165 | C7: Contract/Amendment end date | D7: 120 days after access to data
A8: Who approved business terms | B8: Jason Altieri | C8: Assigned project manager | D8: Jason Altieri
A9: Milliman contract signer | B9: Rich Moyer | C9: Who approved legal terms | D9: Jay Spencer
A10: Products/Services are part of this contract | B10: Consulting | C10: Market segment | D10: Other - Misc
A11: Payer Segment Details: | C11: Provider Segment Details:
A12: BCBS | B12: No | C12: ACO - Commercial | D12: No
A13: Commercial | B13: No | C13: ACO - Medicaid | D13: No
A14: Exchange | B14: No | C14: ACO - MSSP | D14: No
A15: Medicaid | B15: No | C15: ACO - Next Gen | D15: No
A16: Medicare | B16: No | C16: Health System | D16: No
A17: Provider Sponsored | B17: No
A18: Client Contract Owner | C18: Client Billing Contact
A19: Name | B19: Brett Furst | C19: Name | D19: Kevin Mehta
A20: Title | B20: CEO | C20: Title | D20: CTO
A21: Address (if applicable) | D21: 3520 Green Ct, #300; Ann Arbor, MI; 48015
A22: Email | B22: brett@foresightventures.net | C22: Email | D22: Kevin.Mehta@payformancesolutions.com
A23: Phone | B23: 248-496-2584 | C23: Phone
A24: Contract Notification Contact
A25: Name | B25: Legal Dept
A26: Title | B26: 3520 Green Ct., #300; Ann Arbor, MI; 48015
A27: Address
A28: Email
A29: Phone
A31: If MedInsight contract, what Milliman components are included | C31: If Tools contract, what products are included
A32: HCGs | B32: No | C32: HCG Grouper | D32: No
A33: Benchmarks | B33: No | C33: Benchmarks | D33: No
A34: CCHGs | B34: No | C34: CCHG Grouper | D34: No
A35: EBMs | B35: No | C35: HECS | D35: No
A36: GlobalRVUs | B36: No | C36: GlobalRVUs | D36: No
A37: Medicare Repricer | B37: No | C37: Medicare Repricer | D37: No
A38: Waste Calculator | B38: No | C38: Waste Calculator | D38: No
A39: Guideline Analytics | B39: No | C39: Guideline Analytics | D39: No
A40: Solutions included in this contract (MedInsight only)
A41: EGR Solution | B41: No | C41: Care Mgmt Solution | D41: No
A43: List third party tools in this contract
A44: MEGs | B44: No | C44: MARA | D44: No
A45: ETGs | B45: No | C45: ERG | D45: No
A46: MS-DRG | B46: No | C46: DxCG | D46: No
A47: CMS-HCC | B47: No | C47: CDPS | D47: No
A49: Standard MedInsight contract? | B49: Yes | C49: If yes, are there revisions? | D49: Yes
A50: List major contract revisions - terms and SLAs | B50: This is a license for a pilot for PRM data analysis, this is a one time event on the state of Michigan data. Once we receive final approval from the state of Michigan that we may use their data (we currently receive it in the Indy office for consulting purposes) for this pilot, it will commence. If successful, a full license will be executed with Altarum / Payformance for broader utilization.
A51: Rights to client's data? | B51: No | C51: BAA attached w contract? | D51: Yes
A52: Minimum contract reqs in place? Limit of Liability, Dispute Resolution, Third Party Distribution
A53: Membership cap at beginning of contract | B53: 200000 | C53: Membership limits/how are membership increases handled in contract | D53: NA
A54: Termination without cause provision? | B54: No | C54: Payment Terms | D54: net 30
A55: Revenue type | B55: 1-time | C55: Total guaranteed value of contract | D55: 10000
A56: List persons who should receive a copy of face sheet and fully executed contract | B56: Pedersen, Zoelzer, Leonardo, Turner, Andersen, Fessler, Suelzle, Watson, Altieri If Tools, include Fox, Dachary
A57: Did a Milliman (non MedInsight) consultant help with this sale? | B57: No | C57: Cross Credit Terms (if any) and Consultant Name
A58: Renewal Type | B58: Non Automatic | C58: Renewal Inflator % | D58: NA
A59: Renewal Notification Period | B59: Other | C59: Renewal Term | D59: NA
A60: Miscellaneous Notes | B60: This pilot is a one time event. There isn't anything added to the Price Sheet or Allocation tabs as PRM is not part of the Pricer + this is simply a PRM Pilot.
A61: # of authorized users | B61: 5 | C61: Face Sheet Version | D61: Original
A63: v.20171016

Sheet Transition Info
A1: Transition to Implementation Info
A2: To be completed for all MedInsight contracts requiring implementation
A3: Client Legal Name | B3: ='Contract Summary'!B3 -> Payformance Solutions, Inc. (They're a subsidiary of Altarum) | C3: Client Code | D3: ='Contract Summary'!D3 -> 0273PFS01; 0009PFS01
A4: Client Abbreviated Name | B4: ='Contract Summary'!B4 -> Payformance
A5: Contract Term (months) | B5: ='Contract Summary'!D5 -> 120 days after access to data | C5: Org Contract effective date | D5: ='Contract Summary'!B7 -> 43165
A6: Salesperson | B6: ='Contract Summary'!D4 -> McKinley | C6: Contract/amendment end date | D6: ='Contract Summary'!D7 -> 120 days after access to data
A7: Implementation Start Date, if stated in contract | B7: As soon as possible | C7: Implementation End Date, if stated in contract | D7: As soon as possible
A8: Are there penalties or incentives associated with implementation? | B8: No | C8: Describe implementation penalties or incentives | D8: NA
A9: Milliman Project Manager | B9: ='Contract Summary'!D8 -> Jason Altieri | C9: Client Executive Sponsor | D9: Brett Furst
A10: Main Client Contacts during sale (name, title) | B10: Brett Furst, CEO of Foresight Ventures, Kevin Mehta, CTO of Payformance Solutions, Inc.
A11: Client Key Objectives and Business Issues | B11: Evaluate the State of Michigan's data and identify / predict areas for improvement around cost, efficiency, etc.
A12: Key Discussion Topics | B12: Waiting on the State of Michigan to approve use of their data for this pilot, discussion lead is the client
A13: Client Lines of Business (IMPORTANT) | B13: NA | C13: Data Refresh Frequency | D13: NA
A14: Initial Membership | B14: ='Contract Summary'!B53 -> 200000
A15: Number of users | B15: ='Contract Summary'!B61 -> 5 | C15: Non-client-employee users? If yes, describe | D15: 0
A16: Initial # Years History to Load | B16: 3 | C16: Number of data suppliers | D16: 1
A17: List Non Standard File Types (ie lab, EMR, premiums, authorizations) | C17: Any capitation arrangements? If yes, does the encounter data come with the claims file, or separately?
A18: Components/Methodologies Included:
A19: HCGs | B19: ='Contract Summary'!B32 -> No | C19: IBNR
A20: Benchmarks | B20: ='Contract Summary'!B33 -> No | C20: IBNR - Milliman Calculated
A21: CCHGs | B21: ='Contract Summary'!B34 -> No | C21: IBNR - Client Provided
A22: EBMs | B22: ='Contract Summary'!B35 -> No | C22: Physician Attribution
A23: GlobalRVUs | B23: ='Contract Summary'!B36 -> No | C23: Methodology, if known
A24: Medicare Repricer | B24: ='Contract Summary'!B37 -> No | C24: Non Standard:
A25: Waste Calculator | B25: ='Contract Summary'!B38 -> No | C25: ETGs | D25: ='Contract Summary'!B45 -> No
A26: Guideline Analytics | B26: ='Contract Summary'!B39 -> No | C26: ERGs | D26: ='Contract Summary'!D45 -> No
A27: MEGs | B27: ='Contract Summary'!B44 -> No | C27: DxCG | D27: ='Contract Summary'!D46 -> No
A28: MARA | B28: ='Contract Summary'!D44 -> No | C28: CDPS (Medicaid only) | D28: ='Contract Summary'!D47 -> No
A29: MS-DRGs | B29: ='Contract Summary'!B46 -> No | C29: CMS HCC | D29: ='Contract Summary'!B47 -> No
A30: DRGs Client Provided
A31: Solutions included in this contract
A32: ='Contract Summary'!A41 -> EGR Solution | B32: ='Contract Summary'!B41 -> No | C32: ='Contract Summary'!C41 -> Care Mgmt Solution | D32: ='Contract Summary'!D41 -> No
A34: Other Information
A35: Outbound extracts required? | C35: Describe required extracts
A36: Transport database required? | C36: Claims Audit Included?
A37: Other Information relevent to implementation

Sheet Billing Schedule
A1: Implementation billing will be based on work completed previous month. The amounts in the below schedule are just estimates.
A3: 2017 Billing Schedule
A4: Item | B4: Jan | C4: Feb | D4: Mar | E4: Apr | F4: May | G4: Jun | H4: Jul | I4: Aug | J4: Sep | K4: Oct | L4: Nov | M4: Dec | N4: Totals
A5: License Total | N5: =SUM(B5:M5) -> 0
A6: Implementation | N6: =SUM(B6:M6) -> 0
A7: SaaS | N7: =SUM(B7:M7) -> 0
A8: SaaS - Milwaukee | N8: =SUM(B8:M8) -> 0
A9: SaaS - San Diego | N9: =SUM(B9:M9) -> 0
L10: Total | M10: 2017 | N10: =SUM(N5:N9) -> 0
A12: 2018 Billing Schedule
A13: Item | B13: Jan | C13: Feb | D13: Mar | E13: Apr | F13: May | G13: Jun | H13: Jul | I13: Aug | J13: Sep | K13: Oct | L13: Nov | M13: Dec | N13: Totals
A14: License Total | D14: 10000 | N14: =SUM(B14:M14) -> 10000
A15: Implementation | N15: =SUM(B15:M15) -> 0
A16: SaaS | N16: =SUM(B16:M16) -> 0
A17: SaaS - Milwaukee | N17: =SUM(B17:M17) -> 0
A18: SaaS - San Diego | N18: =SUM(B18:M18) -> 0
L19: Total | M19: 2018 | N19: =SUM(N14:N18) -> 10000
A21: 2019 Billing Schedule
A22: Item | B22: Jan | C22: Feb | D22: Mar | E22: Apr | F22: May | G22: Jun | H22: Jul | I22: Aug | J22: Sep | K22: Oct | L22: Nov | M22: Dec | N22: Totals
A23: License Total | N23: =SUM(B23:M23) -> 0
A24: Implementation | N24: =SUM(B24:M24) -> 0
A25: SaaS | N25: =SUM(B25:M25) -> 0
A26: SaaS - Milwaukee | N26: =SUM(B26:M26) -> 0
A27: SaaS - San Diego | N27: =SUM(B27:M27) -> 0
L28: Total | M28: 2019 | N28: =SUM(N23:N27) -> 0
A30: 2020 Billing Schedule
A31: Item | B31: Jan | C31: Feb | D31: Mar | E31: Apr | F31: May | G31: Jun | H31: Jul | I31: Aug | J31: Sep | K31: Oct | L31: Nov | M31: Dec | N31: Totals
A32: License Total | N32: =SUM(B32:M32) -> 0
A33: Implementation | N33: =SUM(B33:M33) -> 0
A34: SaaS | N34: =SUM(B34:M34) -> 0
A35: SaaS - Milwaukee | N35: =SUM(B35:M35) -> 0
A36: SaaS - San Diego | N36: =SUM(B36:M36) -> 0
L37: Total | M37: 2020 | N37: =SUM(N32:N36) -> 0
A39: 2021 Billing Schedule
A40: Item | B40: Jan | C40: Feb | D40: Mar | E40: Apr | F40: May | G40: Jun | H40: Jul | I40: Aug | J40: Sep | K40: Oct | L40: Nov | M40: Dec | N40: Totals
A41: License Total | N41: =SUM(B41:M41) -> 0
A42: Implementation | N42: =SUM(B42:M42) -> 0
A43: SaaS | N43: =SUM(B43:M43) -> 0
A44: SaaS - Milwaukee | N44: =SUM(B44:M44) -> 0
A45: SaaS - San Diego | N45: =SUM(B45:M45) -> 0
L46: Total | M46: 2021 | N46: =SUM(N41:N45) -> 0

Sheet MI Price Sheet

Sheet Allocations

Sheet Lists
A1: New | B1: Wallace | C1: MedInsight | D1: Payer | E1: Yes | F1: net 30 | G1: Recurring | H1: Original | I1: Automatic with Inflator | J1: 30 days | K1: Milliman
A2: Renewal | B2: McKinley | C2: Tools | D2: Provider | E2: No | F2: net 45 | G2: 1-time | H2: Original - revised | I2: Non Automatic | J2: 60 days | K2: Client
A3: CSA | B3: Fessler | C3: Consulting | D3: Government - City | F3: net 60 | H3: Renewal | I3: Other | J3: 90 days | K3: Unknown
A4: Amendment | B4: Pedersen | D4: Government - County | F4: net 90 | H4: Amendment | J4: 120 days
B5: Christiansen | D5: Government - Federal | F5: other | J5: 150 days
B6: Other | D6: State - Employer | J6: 180 days
D7: State - Medicaid | J7: Other
D8: State - Exchange
D9: Multi Payer - APCD
D10: Multi Payer - Coalition
D11: Employer - Small
D12: Employer - Medium
D13: Employer - Large
D14: Employer - Union
D15: Other - Misc
D16: Other - TPA
D17: Other - Milliman
D18: Other - Global Supplier
